{"generated_at": "2026-07-15 16:32 CDT", "now_date": "2026-07-15", "now_he": 17, "points": [{"date": "2026-07-14", "he": 1, "load_fcst": null, "load_act": 57922.7, "solar_fcst": 0.0, "solar_act": 0.07, "wind_fcst": 15307.0, "wind_act": 8887.29, "net_load_fcst": null, "net_load_act": 49035.34, "hsl_outage": 6586.0}, {"date": "2026-07-14", "he": 2, "load_fcst": null, "load_act": 55770.39, "solar_fcst": 0.0, "solar_act": 0.18, "wind_fcst": 13525.0, "wind_act": 7500.42, "net_load_fcst": null, "net_load_act": 48269.79, "hsl_outage": 7131.0}, {"date": "2026-07-14", "he": 3, "load_fcst": null, "load_act": 54280.3, "solar_fcst": 0.0, "solar_act": 0.35, "wind_fcst": 12706.4, "wind_act": 6119.51, "net_load_fcst": null, "net_load_act": 48160.44, "hsl_outage": 7151.0}, {"date": "2026-07-14", "he": 4, "load_fcst": null, "load_act": 53419.38, "solar_fcst": 0.0, "solar_act": 0.33, "wind_fcst": 11887.5, "wind_act": 5306.22, "net_load_fcst": null, "net_load_act": 48112.829999999994, "hsl_outage": 7151.0}, {"date": "2026-07-14", "he": 5, "load_fcst": null, "load_act": 53345.38, "solar_fcst": 0.0, "solar_act": 0.48, "wind_fcst": 10924.2, "wind_act": 4714.92, "net_load_fcst": null, "net_load_act": 48629.979999999996, "hsl_outage": 7151.0}, {"date": "2026-07-14", "he": 6, "load_fcst": null, "load_act": 54138.0, "solar_fcst": 0.0, "solar_act": 0.2, "wind_fcst": 9850.3, "wind_act": 4356.57, "net_load_fcst": null, "net_load_act": 49781.23, "hsl_outage": 7153.0}, {"date": "2026-07-14", "he": 7, "load_fcst": null, "load_act": 55283.67, "solar_fcst": 143.1, "solar_act": 47.55, "wind_fcst": 8571.9, "wind_act": 3913.57, "net_load_fcst": null, "net_load_act": 51322.549999999996, "hsl_outage": 8091.0}, {"date": "2026-07-14", "he": 8, "load_fcst": null, "load_act": 56009.76, "solar_fcst": 4507.7, "solar_act": 2581.89, "wind_fcst": 6882.4, "wind_act": 3388.58, "net_load_fcst": null, "net_load_act": 50039.29, "hsl_outage": 8089.0}, {"date": "2026-07-14", "he": 9, "load_fcst": null, "load_act": 57328.35, "solar_fcst": 14858.3, "solar_act": 8237.12, "wind_fcst": 6064.5, "wind_act": 3120.09, "net_load_fcst": null, "net_load_act": 45971.14, "hsl_outage": 8090.0}, {"date": "2026-07-14", "he": 10, "load_fcst": null, "load_act": 58943.05, "solar_fcst": 21307.0, "solar_act": 13093.27, "wind_fcst": 5247.9, "wind_act": 4002.13, "net_load_fcst": null, "net_load_act": 41847.65, "hsl_outage": 8768.0}, {"date": "2026-07-14", "he": 11, "load_fcst": null, "load_act": 61046.32, "solar_fcst": 24547.1, "solar_act": 16372.9, "wind_fcst": 4650.4, "wind_act": 5632.62, "net_load_fcst": null, "net_load_act": 39040.799999999996, "hsl_outage": 8768.0}, {"date": "2026-07-14", "he": 12, "load_fcst": null, "load_act": 63080.65, "solar_fcst": 26565.4, "solar_act": 17165.64, "wind_fcst": 4287.3, "wind_act": 7343.93, "net_load_fcst": null, "net_load_act": 38571.08, "hsl_outage": 8808.0}, {"date": "2026-07-14", "he": 13, "load_fcst": null, "load_act": 64984.96, "solar_fcst": 26401.9, "solar_act": 18549.34, "wind_fcst": 3922.1, "wind_act": 8004.95, "net_load_fcst": null, "net_load_act": 38430.67, "hsl_outage": 9074.0}, {"date": "2026-07-14", "he": 14, "load_fcst": null, "load_act": 66607.11, "solar_fcst": 25696.6, "solar_act": 19770.27, "wind_fcst": 4057.7, "wind_act": 9074.77, "net_load_fcst": null, "net_load_act": 37762.06999999999, "hsl_outage": 9303.0}, {"date": "2026-07-14", "he": 15, "load_fcst": null, "load_act": 67981.43, "solar_fcst": 25430.4, "solar_act": 20327.65, "wind_fcst": 5222.2, "wind_act": 10750.97, "net_load_fcst": null, "net_load_act": 36902.80999999999, "hsl_outage": 8744.0}, {"date": "2026-07-14", "he": 16, "load_fcst": null, "load_act": 68706.27, "solar_fcst": 24170.0, "solar_act": 19152.11, "wind_fcst": 6391.6, "wind_act": 11885.93, "net_load_fcst": null, "net_load_act": 37668.23, "hsl_outage": 8744.0}, {"date": "2026-07-14", "he": 17, "load_fcst": null, "load_act": 69004.63, "solar_fcst": 21760.4, "solar_act": 17801.43, "wind_fcst": 7604.9, "wind_act": 14557.52, "net_load_fcst": null, "net_load_act": 36645.68000000001, "hsl_outage": 8364.0}, {"date": "2026-07-14", "he": 18, "load_fcst": null, "load_act": 68753.02, "solar_fcst": 18752.8, "solar_act": 16579.11, "wind_fcst": 8851.8, "wind_act": 15466.46, "net_load_fcst": null, "net_load_act": 36707.450000000004, "hsl_outage": 8413.0}, {"date": "2026-07-14", "he": 19, "load_fcst": null, "load_act": 68011.65, "solar_fcst": 14352.0, "solar_act": 13169.82, "wind_fcst": 9509.1, "wind_act": 16160.99, "net_load_fcst": null, "net_load_act": 38680.84, "hsl_outage": 7517.0}, {"date": "2026-07-14", "he": 20, "load_fcst": null, "load_act": 66505.93, "solar_fcst": 6860.9, "solar_act": 7110.94, "wind_fcst": 10158.2, "wind_act": 14784.22, "net_load_fcst": null, "net_load_act": 44610.76999999999, "hsl_outage": 7510.0}, {"date": "2026-07-14", "he": 21, "load_fcst": null, "load_act": 65294.68, "solar_fcst": 732.8, "solar_act": 944.98, "wind_fcst": 10260.5, "wind_act": 11525.36, "net_load_fcst": null, "net_load_act": 52824.34, "hsl_outage": 7487.0}, {"date": "2026-07-14", "he": 22, "load_fcst": null, "load_act": 64173.66, "solar_fcst": 0.0, "solar_act": 0.06, "wind_fcst": 10361.9, "wind_act": 8685.06, "net_load_fcst": null, "net_load_act": 55488.54000000001, "hsl_outage": 7487.0}, {"date": "2026-07-14", "he": 23, "load_fcst": null, "load_act": 61697.48, "solar_fcst": 0.0, "solar_act": 0.06, "wind_fcst": 10218.1, "wind_act": 7766.38, "net_load_fcst": null, "net_load_act": 53931.04000000001, "hsl_outage": 7487.0}, {"date": "2026-07-14", "he": 24, "load_fcst": null, "load_act": 58883.99, "solar_fcst": 0.0, "solar_act": 0.08, "wind_fcst": 9712.4, "wind_act": 7931.68, "net_load_fcst": null, "net_load_act": 50952.229999999996, "hsl_outage": 6688.0}, {"date": "2026-07-15", "he": 1, "load_fcst": 55812.2405, "load_act": null, "solar_fcst": 0.0, "solar_act": 0.19, "wind_fcst": 8969.6, "wind_act": 8553.59, "net_load_fcst": 46842.6405, "net_load_act": null, "hsl_outage": 6688.0}, {"date": "2026-07-15", "he": 2, "load_fcst": 53550.42, "load_act": null, "solar_fcst": 0.0, "solar_act": 0.29, "wind_fcst": 8251.9, "wind_act": 8367.78, "net_load_fcst": 45298.52, "net_load_act": null, "hsl_outage": 6688.0}, {"date": "2026-07-15", "he": 3, "load_fcst": 51839.3906, "load_act": null, "solar_fcst": 0.0, "solar_act": 0.23, "wind_fcst": 6532.9, "wind_act": 7657.27, "net_load_fcst": 45306.4906, "net_load_act": null, "hsl_outage": 6688.0}, {"date": "2026-07-15", "he": 4, "load_fcst": 50700.4902, "load_act": null, "solar_fcst": 0.0, "solar_act": 0.38, "wind_fcst": 5681.6, "wind_act": 6730.62, "net_load_fcst": 45018.8902, "net_load_act": null, "hsl_outage": 6688.0}, {"date": "2026-07-15", "he": 5, "load_fcst": 50502.279800000004, "load_act": null, "solar_fcst": 0.0, "solar_act": 0.48, "wind_fcst": 4902.7, "wind_act": 5866.41, "net_load_fcst": 45599.57980000001, "net_load_act": null, "hsl_outage": 6688.0}, {"date": "2026-07-15", "he": 6, "load_fcst": 51256.280399999996, "load_act": null, "solar_fcst": 0.0, "solar_act": 0.44, "wind_fcst": 4209.2, "wind_act": 5936.82, "net_load_fcst": 47047.0804, "net_load_act": null, "hsl_outage": 6688.0}, {"date": "2026-07-15", "he": 7, "load_fcst": 52679.0407, "load_act": null, "solar_fcst": 124.2, "solar_act": 72.31, "wind_fcst": 3483.3, "wind_act": 6180.49, "net_load_fcst": 49071.5407, "net_load_act": null, "hsl_outage": 6707.0}, {"date": "2026-07-15", "he": 8, "load_fcst": 53525.3998, "load_act": null, "solar_fcst": 3761.8, "solar_act": 3067.06, "wind_fcst": 3302.0, "wind_act": 5874.76, "net_load_fcst": 46461.599799999996, "net_load_act": null, "hsl_outage": 6707.0}, {"date": "2026-07-15", "he": 9, "load_fcst": 55324.7994, "load_act": null, "solar_fcst": 11909.3, "solar_act": 9478.23, "wind_fcst": 3382.2, "wind_act": 5756.76, "net_load_fcst": 40033.2994, "net_load_act": null, "hsl_outage": 6708.0}, {"date": "2026-07-15", "he": 10, "load_fcst": 57647.3909, "load_act": null, "solar_fcst": 17285.1, "solar_act": 14885.0, "wind_fcst": 3448.6, "wind_act": 6180.58, "net_load_fcst": 36913.6909, "net_load_act": null, "hsl_outage": 6674.0}, {"date": "2026-07-15", "he": 11, "load_fcst": 60252.6796, "load_act": null, "solar_fcst": 20559.7, "solar_act": 16791.5, "wind_fcst": 3638.0, "wind_act": 6345.74, "net_load_fcst": 36054.979600000006, "net_load_act": null, "hsl_outage": 6674.0}, {"date": "2026-07-15", "he": 12, "load_fcst": 62877.1703, "load_act": null, "solar_fcst": 22877.0, "solar_act": 17222.9, "wind_fcst": 3973.0, "wind_act": 6514.97, "net_load_fcst": 36027.1703, "net_load_act": null, "hsl_outage": 6674.0}, {"date": "2026-07-15", "he": 13, "load_fcst": 65277.010800000004, "load_act": null, "solar_fcst": 24476.7, "solar_act": 18554.68, "wind_fcst": 4257.5, "wind_act": 6653.61, "net_load_fcst": 36542.81080000001, "net_load_act": null, "hsl_outage": 6673.0}, {"date": "2026-07-15", "he": 14, "load_fcst": 67537.2218, "load_act": null, "solar_fcst": 24779.0, "solar_act": 19863.6, "wind_fcst": 5283.8, "wind_act": 6583.44, "net_load_fcst": 37474.4218, "net_load_act": null, "hsl_outage": 6663.0}, {"date": "2026-07-15", "he": 15, "load_fcst": 69129.4898, "load_act": null, "solar_fcst": 24674.9, "solar_act": 19191.3, "wind_fcst": 6206.5, "wind_act": 6842.78, "net_load_fcst": 38248.089799999994, "net_load_act": null, "hsl_outage": 6663.0}, {"date": "2026-07-15", "he": 16, "load_fcst": 70249.20910000001, "load_act": null, "solar_fcst": 23326.4, "solar_act": null, "wind_fcst": 7123.2, "wind_act": null, "net_load_fcst": 39799.60910000001, "net_load_act": null, "hsl_outage": 6663.0}, {"date": "2026-07-15", "he": 17, "load_fcst": 70891.6609, "load_act": null, "solar_fcst": 20815.5, "solar_act": null, "wind_fcst": 8002.7, "wind_act": null, "net_load_fcst": 42073.460900000005, "net_load_act": null, "hsl_outage": 6644.0}, {"date": "2026-07-15", "he": 18, "load_fcst": 70632.8118, "load_act": null, "solar_fcst": 18263.5, "solar_act": null, "wind_fcst": 8835.0, "wind_act": null, "net_load_fcst": 43534.311799999996, "net_load_act": null, "hsl_outage": 6583.0}, {"date": "2026-07-15", "he": 19, "load_fcst": 69631.8705, "load_act": null, "solar_fcst": 13824.0, "solar_act": null, "wind_fcst": 10204.3, "wind_act": null, "net_load_fcst": 45603.5705, "net_load_act": null, "hsl_outage": 6583.0}, {"date": "2026-07-15", "he": 20, "load_fcst": 67840.0898, "load_act": null, "solar_fcst": 6820.9, "solar_act": null, "wind_fcst": 10821.7, "wind_act": null, "net_load_fcst": 50197.489799999996, "net_load_act": null, "hsl_outage": 6583.0}, {"date": "2026-07-15", "he": 21, "load_fcst": 66206.0597, "load_act": null, "solar_fcst": 686.5, "solar_act": null, "wind_fcst": 11232.7, "wind_act": null, "net_load_fcst": 54286.8597, "net_load_act": null, "hsl_outage": 6583.0}, {"date": "2026-07-15", "he": 22, "load_fcst": 64770.2808, "load_act": null, "solar_fcst": 0.0, "solar_act": null, "wind_fcst": 11632.8, "wind_act": null, "net_load_fcst": 53137.480800000005, "net_load_act": null, "hsl_outage": 6583.0}, {"date": "2026-07-15", "he": 23, "load_fcst": 61862.1296, "load_act": null, "solar_fcst": 0.0, "solar_act": null, "wind_fcst": 11809.2, "wind_act": null, "net_load_fcst": 50052.9296, "net_load_act": null, "hsl_outage": 6583.0}, {"date": "2026-07-15", "he": 24, "load_fcst": 58755.4998, "load_act": null, "solar_fcst": 0.0, "solar_act": null, "wind_fcst": 11744.5, "wind_act": null, "net_load_fcst": 47010.9998, "net_load_act": null, "hsl_outage": 6338.0}, {"date": "2026-07-16", "he": 1, "load_fcst": 55771.630300000004, "load_act": null, "solar_fcst": 0.0, "solar_act": null, "wind_fcst": 13040.9, "wind_act": null, "net_load_fcst": 42730.7303, "net_load_act": null, "hsl_outage": 6338.0}, {"date": "2026-07-16", "he": 2, "load_fcst": 53379.7402, "load_act": null, "solar_fcst": 0.0, "solar_act": null, "wind_fcst": 12337.9, "wind_act": null, "net_load_fcst": 41041.8402, "net_load_act": null, "hsl_outage": 6338.0}, {"date": "2026-07-16", "he": 3, "load_fcst": 51611.0699, "load_act": null, "solar_fcst": 0.0, "solar_act": null, "wind_fcst": 11417.8, "wind_act": null, "net_load_fcst": 40193.2699, "net_load_act": null, "hsl_outage": 6338.0}, {"date": "2026-07-16", "he": 4, "load_fcst": 50638.2496, "load_act": null, "solar_fcst": 0.0, "solar_act": null, "wind_fcst": 10469.6, "wind_act": null, "net_load_fcst": 40168.649600000004, "net_load_act": null, "hsl_outage": 6338.0}, {"date": "2026-07-16", "he": 5, "load_fcst": 50604.8602, "load_act": null, "solar_fcst": 0.0, "solar_act": null, "wind_fcst": 9562.8, "wind_act": null, "net_load_fcst": 41042.06020000001, "net_load_act": null, "hsl_outage": 6338.0}, {"date": "2026-07-16", "he": 6, "load_fcst": 51913.2394, "load_act": null, "solar_fcst": 0.0, "solar_act": null, "wind_fcst": 8705.2, "wind_act": null, "net_load_fcst": 43208.039399999994, "net_load_act": null, "hsl_outage": 6338.0}, {"date": "2026-07-16", "he": 7, "load_fcst": 53526.6201, "load_act": null, "solar_fcst": 129.6, "solar_act": null, "wind_fcst": 9211.9, "wind_act": null, "net_load_fcst": 44185.1201, "net_load_act": null, "hsl_outage": 6338.0}, {"date": "2026-07-16", "he": 8, "load_fcst": 54625.5103, "load_act": null, "solar_fcst": 3911.3, "solar_act": null, "wind_fcst": 8869.0, "wind_act": null, "net_load_fcst": 41845.2103, "net_load_act": null, "hsl_outage": 6528.0}, {"date": "2026-07-16", "he": 9, "load_fcst": 56827.96, "load_act": null, "solar_fcst": 12204.4, "solar_act": null, "wind_fcst": 9411.8, "wind_act": null, "net_load_fcst": 35211.759999999995, "net_load_act": null, "hsl_outage": 6620.0}, {"date": "2026-07-16", "he": 10, "load_fcst": 59627.4697, "load_act": null, "solar_fcst": 17594.6, "solar_act": null, "wind_fcst": 9956.2, "wind_act": null, "net_load_fcst": 32076.669700000002, "net_load_act": null, "hsl_outage": 6619.0}, {"date": "2026-07-16", "he": 11, "load_fcst": 62702.5803, "load_act": null, "solar_fcst": 21379.4, "solar_act": null, "wind_fcst": 10504.5, "wind_act": null, "net_load_fcst": 30818.6803, "net_load_act": null, "hsl_outage": 6623.0}, {"date": "2026-07-16", "he": 12, "load_fcst": 65932.2899, "load_act": null, "solar_fcst": 23388.5, "solar_act": null, "wind_fcst": 11053.9, "wind_act": null, "net_load_fcst": 31489.889900000002, "net_load_act": null, "hsl_outage": 6581.0}, {"date": "2026-07-16", "he": 13, "load_fcst": 68680.8598, "load_act": null, "solar_fcst": 25833.7, "solar_act": null, "wind_fcst": 11602.1, "wind_act": null, "net_load_fcst": 31245.05980000001, "net_load_act": null, "hsl_outage": 6581.0}, {"date": "2026-07-16", "he": 14, "load_fcst": 71170.2095, "load_act": null, "solar_fcst": 27894.6, "solar_act": null, "wind_fcst": 13944.6, "wind_act": null, "net_load_fcst": 29331.0095, "net_load_act": null, "hsl_outage": 6781.0}, {"date": "2026-07-16", "he": 15, "load_fcst": 72503.3489, "load_act": null, "solar_fcst": 28053.1, "solar_act": null, "wind_fcst": 15432.5, "wind_act": null, "net_load_fcst": 29017.7489, "net_load_act": null, "hsl_outage": 6781.0}, {"date": "2026-07-16", "he": 16, "load_fcst": 73328.6812, "load_act": null, "solar_fcst": 26972.5, "solar_act": null, "wind_fcst": 16916.6, "wind_act": null, "net_load_fcst": 29439.581200000008, "net_load_act": null, "hsl_outage": 6781.0}, {"date": "2026-07-16", "he": 17, "load_fcst": 73351.8602, "load_act": null, "solar_fcst": 25814.9, "solar_act": null, "wind_fcst": 18285.0, "wind_act": null, "net_load_fcst": 29251.960199999994, "net_load_act": null, "hsl_outage": 6581.0}, {"date": "2026-07-16", "he": 18, "load_fcst": 72508.7892, "load_act": null, "solar_fcst": 23719.3, "solar_act": null, "wind_fcst": 19514.2, "wind_act": null, "net_load_fcst": 29275.289199999996, "net_load_act": null, "hsl_outage": 6507.0}, {"date": "2026-07-16", "he": 19, "load_fcst": 70834.5596, "load_act": null, "solar_fcst": 19107.1, "solar_act": null, "wind_fcst": 20740.1, "wind_act": null, "net_load_fcst": 30987.359599999996, "net_load_act": null, "hsl_outage": 6325.0}, {"date": "2026-07-16", "he": 20, "load_fcst": 68974.5704, "load_act": null, "solar_fcst": 8810.1, "solar_act": null, "wind_fcst": 21553.4, "wind_act": null, "net_load_fcst": 38611.0704, "net_load_act": null, "hsl_outage": 6325.0}, {"date": "2026-07-16", "he": 21, "load_fcst": 67345.41990000001, "load_act": null, "solar_fcst": 797.8, "solar_act": null, "wind_fcst": 21806.7, "wind_act": null, "net_load_fcst": 44740.91990000001, "net_load_act": null, "hsl_outage": 6135.0}, {"date": "2026-07-16", "he": 22, "load_fcst": 65825.3591, "load_act": null, "solar_fcst": 0.0, "solar_act": null, "wind_fcst": 21935.9, "wind_act": null, "net_load_fcst": 43889.4591, "net_load_act": null, "hsl_outage": 6135.0}, {"date": "2026-07-16", "he": 23, "load_fcst": 63159.8402, "load_act": null, "solar_fcst": 0.0, "solar_act": null, "wind_fcst": 22161.2, "wind_act": null, "net_load_fcst": 40998.640199999994, "net_load_act": null, "hsl_outage": 6135.0}, {"date": "2026-07-16", "he": 24, "load_fcst": 60084.4097, "load_act": null, "solar_fcst": 0.0, "solar_act": null, "wind_fcst": 22512.5, "wind_act": null, "net_load_fcst": 37571.9097, "net_load_act": null, "hsl_outage": 5729.0}, {"date": "2026-07-17", "he": 1, "load_fcst": 57540.0299, "load_act": null, "solar_fcst": 0.0, "solar_act": null, "wind_fcst": 22879.1, "wind_act": null, "net_load_fcst": 34660.9299, "net_load_act": null, "hsl_outage": 5723.0}, {"date": "2026-07-17", "he": 2, "load_fcst": 55239.0899, "load_act": null, "solar_fcst": 0.0, "solar_act": null, "wind_fcst": 20651.4, "wind_act": null, "net_load_fcst": 34587.6899, "net_load_act": null, "hsl_outage": 5723.0}, {"date": "2026-07-17", "he": 3, "load_fcst": 53583.4495, "load_act": null, "solar_fcst": 0.0, "solar_act": null, "wind_fcst": 20060.8, "wind_act": null, "net_load_fcst": 33522.6495, "net_load_act": null, "hsl_outage": 5723.0}, {"date": "2026-07-17", "he": 4, "load_fcst": 52587.5094, "load_act": null, "solar_fcst": 0.0, "solar_act": null, "wind_fcst": 19471.2, "wind_act": null, "net_load_fcst": 33116.3094, "net_load_act": null, "hsl_outage": 5723.0}, {"date": "2026-07-17", "he": 5, "load_fcst": 52515.4096, "load_act": null, "solar_fcst": 0.0, "solar_act": null, "wind_fcst": 18792.4, "wind_act": null, "net_load_fcst": 33723.0096, "net_load_act": null, "hsl_outage": 5723.0}, {"date": "2026-07-17", "he": 6, "load_fcst": 53776.4599, "load_act": null, "solar_fcst": 0.0, "solar_act": null, "wind_fcst": 18032.5, "wind_act": null, "net_load_fcst": 35743.9599, "net_load_act": null, "hsl_outage": 5723.0}, {"date": "2026-07-17", "he": 7, "load_fcst": 55174.9988, "load_act": null, "solar_fcst": 149.2, "solar_act": null, "wind_fcst": 17769.3, "wind_act": null, "net_load_fcst": 37256.4988, "net_load_act": null, "hsl_outage": 5723.0}, {"date": "2026-07-17", "he": 8, "load_fcst": 56311.7792, "load_act": null, "solar_fcst": 5186.9, "solar_act": null, "wind_fcst": 17715.6, "wind_act": null, "net_load_fcst": 33409.2792, "net_load_act": null, "hsl_outage": 5723.0}, {"date": "2026-07-17", "he": 9, "load_fcst": 58779.390400000004, "load_act": null, "solar_fcst": 17136.5, "solar_act": null, "wind_fcst": 17518.6, "wind_act": null, "net_load_fcst": 24124.290400000005, "net_load_act": null, "hsl_outage": 5784.0}, {"date": "2026-07-17", "he": 10, "load_fcst": 61906.809799999995, "load_act": null, "solar_fcst": 24372.6, "solar_act": null, "wind_fcst": 17291.2, "wind_act": null, "net_load_fcst": 20243.009799999996, "net_load_act": null, "hsl_outage": 5784.0}, {"date": "2026-07-17", "he": 11, "load_fcst": 65410.4712, "load_act": null, "solar_fcst": 28101.1, "solar_act": null, "wind_fcst": 16947.9, "wind_act": null, "net_load_fcst": 20361.4712, "net_load_act": null, "hsl_outage": 5733.0}, {"date": "2026-07-17", "he": 12, "load_fcst": 68908.7795, "load_act": null, "solar_fcst": 30275.4, "solar_act": null, "wind_fcst": 16458.8, "wind_act": null, "net_load_fcst": 22174.579500000003, "net_load_act": null, "hsl_outage": 5733.0}, {"date": "2026-07-17", "he": 13, "load_fcst": 72119.9094, "load_act": null, "solar_fcst": 31756.4, "solar_act": null, "wind_fcst": 15973.0, "wind_act": null, "net_load_fcst": 24390.509400000003, "net_load_act": null, "hsl_outage": 5672.0}, {"date": "2026-07-17", "he": 14, "load_fcst": 75057.1904, "load_act": null, "solar_fcst": 31597.3, "solar_act": null, "wind_fcst": 15522.3, "wind_act": null, "net_load_fcst": 27937.590400000005, "net_load_act": null, "hsl_outage": 5672.0}, {"date": "2026-07-17", "he": 15, "load_fcst": 76675.8895, "load_act": null, "solar_fcst": 31613.2, "solar_act": null, "wind_fcst": 16271.5, "wind_act": null, "net_load_fcst": 28791.189500000008, "net_load_act": null, "hsl_outage": 5672.0}, {"date": "2026-07-17", "he": 16, "load_fcst": 77479.8685, "load_act": null, "solar_fcst": 31020.4, "solar_act": null, "wind_fcst": 17029.7, "wind_act": null, "net_load_fcst": 29429.768499999995, "net_load_act": null, "hsl_outage": 5672.0}, {"date": "2026-07-17", "he": 17, "load_fcst": 77453.2189, "load_act": null, "solar_fcst": 29871.9, "solar_act": null, "wind_fcst": 17663.1, "wind_act": null, "net_load_fcst": 29918.218900000007, "net_load_act": null, "hsl_outage": 5672.0}, {"date": "2026-07-17", "he": 18, "load_fcst": 76752.919, "load_act": null, "solar_fcst": 27039.3, "solar_act": null, "wind_fcst": 18230.2, "wind_act": null, "net_load_fcst": 31483.41899999999, "net_load_act": null, "hsl_outage": 5668.0}, {"date": "2026-07-17", "he": 19, "load_fcst": 75026.0809, "load_act": null, "solar_fcst": 21754.9, "solar_act": null, "wind_fcst": 19247.2, "wind_act": null, "net_load_fcst": 34023.980899999995, "net_load_act": null, "hsl_outage": 5607.0}, {"date": "2026-07-17", "he": 20, "load_fcst": 72699.0102, "load_act": null, "solar_fcst": 9896.4, "solar_act": null, "wind_fcst": 19397.6, "wind_act": null, "net_load_fcst": 43405.010200000004, "net_load_act": null, "hsl_outage": 5457.0}, {"date": "2026-07-17", "he": 21, "load_fcst": 70454.4188, "load_act": null, "solar_fcst": 937.2, "solar_act": null, "wind_fcst": 19407.9, "wind_act": null, "net_load_fcst": 50109.3188, "net_load_act": null, "hsl_outage": 5457.0}, {"date": "2026-07-17", "he": 22, "load_fcst": 68895.9704, "load_act": null, "solar_fcst": 0.0, "solar_act": null, "wind_fcst": 19392.5, "wind_act": null, "net_load_fcst": 49503.470400000006, "net_load_act": null, "hsl_outage": 5457.0}, {"date": "2026-07-17", "he": 23, "load_fcst": 66130.3605, "load_act": null, "solar_fcst": 0.0, "solar_act": null, "wind_fcst": 19485.1, "wind_act": null, "net_load_fcst": 46645.2605, "net_load_act": null, "hsl_outage": 5393.0}, {"date": "2026-07-17", "he": 24, "load_fcst": 62948.349, "load_act": null, "solar_fcst": 0.0, "solar_act": null, "wind_fcst": 19702.5, "wind_act": null, "net_load_fcst": 43245.849, "net_load_act": null, "hsl_outage": 4288.0}, {"date": "2026-07-18", "he": 1, "load_fcst": 59821.4093, "load_act": null, "solar_fcst": 0.0, "solar_act": null, "wind_fcst": 20037.6, "wind_act": null, "net_load_fcst": 39783.8093, "net_load_act": null, "hsl_outage": 4288.0}, {"date": "2026-07-18", "he": 2, "load_fcst": 57068.6005, "load_act": null, "solar_fcst": 0.0, "solar_act": null, "wind_fcst": 21126.1, "wind_act": null, "net_load_fcst": 35942.5005, "net_load_act": null, "hsl_outage": 4288.0}, {"date": "2026-07-18", "he": 3, "load_fcst": 54859.779, "load_act": null, "solar_fcst": 0.0, "solar_act": null, "wind_fcst": 20097.5, "wind_act": null, "net_load_fcst": 34762.279, "net_load_act": null, "hsl_outage": 4288.0}, {"date": "2026-07-18", "he": 4, "load_fcst": 53502.3891, "load_act": null, "solar_fcst": 0.0, "solar_act": null, "wind_fcst": 19072.0, "wind_act": null, "net_load_fcst": 34430.3891, "net_load_act": null, "hsl_outage": 4288.0}, {"date": "2026-07-18", "he": 5, "load_fcst": 52616.2391, "load_act": null, "solar_fcst": 0.0, "solar_act": null, "wind_fcst": 18042.7, "wind_act": null, "net_load_fcst": 34573.539099999995, "net_load_act": null, "hsl_outage": 4288.0}, {"date": "2026-07-18", "he": 6, "load_fcst": 52719.15, "load_act": null, "solar_fcst": 0.0, "solar_act": null, "wind_fcst": 17021.1, "wind_act": null, "net_load_fcst": 35698.05, "net_load_act": null, "hsl_outage": 4288.0}, {"date": "2026-07-18", "he": 7, "load_fcst": 52603.2001, "load_act": null, "solar_fcst": 138.7, "solar_act": null, "wind_fcst": 16761.9, "wind_act": null, "net_load_fcst": 35702.6001, "net_load_act": null, "hsl_outage": 4288.0}, {"date": "2026-07-18", "he": 8, "load_fcst": 53346.5506, "load_act": null, "solar_fcst": 5033.2, "solar_act": null, "wind_fcst": 16636.1, "wind_act": null, "net_load_fcst": 31677.250600000007, "net_load_act": null, "hsl_outage": 4288.0}, {"date": "2026-07-18", "he": 9, "load_fcst": 56428.7998, "load_act": null, "solar_fcst": 16564.2, "solar_act": null, "wind_fcst": 16412.7, "wind_act": null, "net_load_fcst": 23451.899799999996, "net_load_act": null, "hsl_outage": 4288.0}, {"date": "2026-07-18", "he": 10, "load_fcst": 60497.7308, "load_act": null, "solar_fcst": 23636.4, "solar_act": null, "wind_fcst": 16185.5, "wind_act": null, "net_load_fcst": 20675.830799999996, "net_load_act": null, "hsl_outage": 4288.0}, {"date": "2026-07-18", "he": 11, "load_fcst": 64715.129199999996, "load_act": null, "solar_fcst": 27560.3, "solar_act": null, "wind_fcst": 15997.9, "wind_act": null, "net_load_fcst": 21156.92919999999, "net_load_act": null, "hsl_outage": 4288.0}, {"date": "2026-07-18", "he": 12, "load_fcst": 68931.3694, "load_act": null, "solar_fcst": 30354.3, "solar_act": null, "wind_fcst": 15857.1, "wind_act": null, "net_load_fcst": 22719.969399999994, "net_load_act": null, "hsl_outage": 4288.0}, {"date": "2026-07-18", "he": 13, "load_fcst": 72563.2501, "load_act": null, "solar_fcst": 30986.7, "solar_act": null, "wind_fcst": 15644.8, "wind_act": null, "net_load_fcst": 25931.75010000001, "net_load_act": null, "hsl_outage": 4288.0}, {"date": "2026-07-18", "he": 14, "load_fcst": 75412.5589, "load_act": null, "solar_fcst": 31421.7, "solar_act": null, "wind_fcst": 16010.6, "wind_act": null, "net_load_fcst": 27980.258900000008, "net_load_act": null, "hsl_outage": 4288.0}, {"date": "2026-07-18", "he": 15, "load_fcst": 77418.2085, "load_act": null, "solar_fcst": 31527.4, "solar_act": null, "wind_fcst": 17206.1, "wind_act": null, "net_load_fcst": 28684.708499999993, "net_load_act": null, "hsl_outage": 4288.0}, {"date": "2026-07-18", "he": 16, "load_fcst": 78688.0107, "load_act": null, "solar_fcst": 30912.1, "solar_act": null, "wind_fcst": 18397.7, "wind_act": null, "net_load_fcst": 29378.2107, "net_load_act": null, "hsl_outage": 4288.0}, {"date": "2026-07-18", "he": 17, "load_fcst": 79161.8201, "load_act": null, "solar_fcst": 29334.9, "solar_act": null, "wind_fcst": 19434.4, "wind_act": null, "net_load_fcst": 30392.520099999994, "net_load_act": null, "hsl_outage": 4288.0}, {"date": "2026-07-18", "he": 18, "load_fcst": 78760.9803, "load_act": null, "solar_fcst": 26932.6, "solar_act": null, "wind_fcst": 20296.6, "wind_act": null, "net_load_fcst": 31531.7803, "net_load_act": null, "hsl_outage": 4288.0}, {"date": "2026-07-18", "he": 19, "load_fcst": 77303.0088, "load_act": null, "solar_fcst": 21756.3, "solar_act": null, "wind_fcst": 21119.1, "wind_act": null, "net_load_fcst": 34427.608799999995, "net_load_act": null, "hsl_outage": 4288.0}, {"date": "2026-07-18", "he": 20, "load_fcst": 74988.6211, "load_act": null, "solar_fcst": 10623.0, "solar_act": null, "wind_fcst": 21757.8, "wind_act": null, "net_load_fcst": 42607.8211, "net_load_act": null, "hsl_outage": 4288.0}, {"date": "2026-07-18", "he": 21, "load_fcst": 72367.2208, "load_act": null, "solar_fcst": 953.6, "solar_act": null, "wind_fcst": 21838.7, "wind_act": null, "net_load_fcst": 49574.92079999999, "net_load_act": null, "hsl_outage": 4288.0}, {"date": "2026-07-18", "he": 22, "load_fcst": 70621.6704, "load_act": null, "solar_fcst": 0.0, "solar_act": null, "wind_fcst": 21478.5, "wind_act": null, "net_load_fcst": 49143.1704, "net_load_act": null, "hsl_outage": 4288.0}, {"date": "2026-07-18", "he": 23, "load_fcst": 67788.3285, "load_act": null, "solar_fcst": 0.0, "solar_act": null, "wind_fcst": 21075.8, "wind_act": null, "net_load_fcst": 46712.5285, "net_load_act": null, "hsl_outage": 4288.0}, {"date": "2026-07-18", "he": 24, "load_fcst": 64381.650200000004, "load_act": null, "solar_fcst": 0.0, "solar_act": null, "wind_fcst": 20523.0, "wind_act": null, "net_load_fcst": 43858.650200000004, "net_load_act": null, "hsl_outage": 4288.0}, {"date": "2026-07-19", "he": 1, "load_fcst": 61146.4795, "load_act": null, "solar_fcst": 0.0, "solar_act": null, "wind_fcst": 19992.2, "wind_act": null, "net_load_fcst": 41154.279500000004, "net_load_act": null, "hsl_outage": 4288.0}, {"date": "2026-07-19", "he": 2, "load_fcst": 58343.1395, "load_act": null, "solar_fcst": 0.0, "solar_act": null, "wind_fcst": 19267.3, "wind_act": null, "net_load_fcst": 39075.8395, "net_load_act": null, "hsl_outage": 4288.0}, {"date": "2026-07-19", "he": 3, "load_fcst": 56071.64, "load_act": null, "solar_fcst": 0.0, "solar_act": null, "wind_fcst": 17948.3, "wind_act": null, "net_load_fcst": 38123.34, "net_load_act": null, "hsl_outage": 4288.0}, {"date": "2026-07-19", "he": 4, "load_fcst": 54550.9099, "load_act": null, "solar_fcst": 0.0, "solar_act": null, "wind_fcst": 16628.5, "wind_act": null, "net_load_fcst": 37922.4099, "net_load_act": null, "hsl_outage": 4288.0}, {"date": "2026-07-19", "he": 5, "load_fcst": 53446.3799, "load_act": null, "solar_fcst": 0.0, "solar_act": null, "wind_fcst": 15337.8, "wind_act": null, "net_load_fcst": 38108.5799, "net_load_act": null, "hsl_outage": 4288.0}, {"date": "2026-07-19", "he": 6, "load_fcst": 53014.47, "load_act": null, "solar_fcst": 0.0, "solar_act": null, "wind_fcst": 14080.9, "wind_act": null, "net_load_fcst": 38933.57, "net_load_act": null, "hsl_outage": 4288.0}, {"date": "2026-07-19", "he": 7, "load_fcst": 52418.5603, "load_act": null, "solar_fcst": 143.6, "solar_act": null, "wind_fcst": 13860.3, "wind_act": null, "net_load_fcst": 38414.6603, "net_load_act": null, "hsl_outage": 4288.0}, {"date": "2026-07-19", "he": 8, "load_fcst": 52915.0005, "load_act": null, "solar_fcst": 5606.0, "solar_act": null, "wind_fcst": 13370.0, "wind_act": null, "net_load_fcst": 33939.0005, "net_load_act": null, "hsl_outage": 4288.0}, {"date": "2026-07-19", "he": 9, "load_fcst": 56391.200600000004, "load_act": null, "solar_fcst": 18954.3, "solar_act": null, "wind_fcst": 12762.0, "wind_act": null, "net_load_fcst": 24674.900600000008, "net_load_act": null, "hsl_outage": 4288.0}, {"date": "2026-07-19", "he": 10, "load_fcst": 60835.5195, "load_act": null, "solar_fcst": 26976.7, "solar_act": null, "wind_fcst": 12155.0, "wind_act": null, "net_load_fcst": 21703.819499999998, "net_load_act": null, "hsl_outage": 4288.0}, {"date": "2026-07-19", "he": 11, "load_fcst": 65281.7289, "load_act": null, "solar_fcst": 30414.6, "solar_act": null, "wind_fcst": 11475.0, "wind_act": null, "net_load_fcst": 23392.128900000003, "net_load_act": null, "hsl_outage": 4288.0}, {"date": "2026-07-19", "he": 12, "load_fcst": 69634.2, "load_act": null, "solar_fcst": 32366.6, "solar_act": null, "wind_fcst": 10711.5, "wind_act": null, "net_load_fcst": 26556.1, "net_load_act": null, "hsl_outage": 4288.0}, {"date": "2026-07-19", "he": 13, "load_fcst": 73469.7288, "load_act": null, "solar_fcst": 32747.3, "solar_act": null, "wind_fcst": 9014.8, "wind_act": null, "net_load_fcst": 31707.628799999995, "net_load_act": null, "hsl_outage": 4288.0}, {"date": "2026-07-19", "he": 14, "load_fcst": 76769.12, "load_act": null, "solar_fcst": 33062.3, "solar_act": null, "wind_fcst": 11416.4, "wind_act": null, "net_load_fcst": 32290.41999999999, "net_load_act": null, "hsl_outage": 4288.0}, {"date": "2026-07-19", "he": 15, "load_fcst": 79122.9902, "load_act": null, "solar_fcst": 33085.3, "solar_act": null, "wind_fcst": 12409.4, "wind_act": null, "net_load_fcst": 33628.290199999996, "net_load_act": null, "hsl_outage": 4288.0}, {"date": "2026-07-19", "he": 16, "load_fcst": 80641.8702, "load_act": null, "solar_fcst": 32541.9, "solar_act": null, "wind_fcst": 13403.3, "wind_act": null, "net_load_fcst": 34696.67020000001, "net_load_act": null, "hsl_outage": 4288.0}, {"date": "2026-07-19", "he": 17, "load_fcst": 81261.0508, "load_act": null, "solar_fcst": 31746.9, "solar_act": null, "wind_fcst": 14315.0, "wind_act": null, "net_load_fcst": 35199.150799999996, "net_load_act": null, "hsl_outage": 4288.0}, {"date": "2026-07-19", "he": 18, "load_fcst": 81332.2301, "load_act": null, "solar_fcst": 30144.1, "solar_act": null, "wind_fcst": 15129.1, "wind_act": null, "net_load_fcst": 36059.0301, "net_load_act": null, "hsl_outage": 4288.0}, {"date": "2026-07-19", "he": 19, "load_fcst": 80346.8498, "load_act": null, "solar_fcst": 25309.8, "solar_act": null, "wind_fcst": 17695.5, "wind_act": null, "net_load_fcst": 37341.54979999999, "net_load_act": null, "hsl_outage": 4288.0}, {"date": "2026-07-19", "he": 20, "load_fcst": 78311.80040000001, "load_act": null, "solar_fcst": 11447.4, "solar_act": null, "wind_fcst": 18266.7, "wind_act": null, "net_load_fcst": 48597.700400000016, "net_load_act": null, "hsl_outage": 4288.0}, {"date": "2026-07-19", "he": 21, "load_fcst": 75644.8884, "load_act": null, "solar_fcst": 1025.4, "solar_act": null, "wind_fcst": 19301.4, "wind_act": null, "net_load_fcst": 55318.0884, "net_load_act": null, "hsl_outage": 4288.0}, {"date": "2026-07-19", "he": 22, "load_fcst": 73635.9293, "load_act": null, "solar_fcst": 0.0, "solar_act": null, "wind_fcst": 19628.4, "wind_act": null, "net_load_fcst": 54007.5293, "net_load_act": null, "hsl_outage": 4288.0}, {"date": "2026-07-19", "he": 23, "load_fcst": 70010.7306, "load_act": null, "solar_fcst": 0.0, "solar_act": null, "wind_fcst": 19873.1, "wind_act": null, "net_load_fcst": 50137.6306, "net_load_act": null, "hsl_outage": 4288.0}, {"date": "2026-07-19", "he": 24, "load_fcst": 65792.1186, "load_act": null, "solar_fcst": 0.0, "solar_act": null, "wind_fcst": 20024.0, "wind_act": null, "net_load_fcst": 45768.1186, "net_load_act": null, "hsl_outage": 4288.0}, {"date": "2026-07-20", "he": 1, "load_fcst": 61713.5408, "load_act": null, "solar_fcst": 0.0, "solar_act": null, "wind_fcst": 20182.6, "wind_act": null, "net_load_fcst": 41530.940800000004, "net_load_act": null, "hsl_outage": 4288.0}, {"date": "2026-07-20", "he": 2, "load_fcst": 58433.8993, "load_act": null, "solar_fcst": 0.0, "solar_act": null, "wind_fcst": 18863.6, "wind_act": null, "net_load_fcst": 39570.2993, "net_load_act": null, "hsl_outage": 4288.0}, {"date": "2026-07-20", "he": 3, "load_fcst": 55936.6497, "load_act": null, "solar_fcst": 0.0, "solar_act": null, "wind_fcst": 17681.1, "wind_act": null, "net_load_fcst": 38255.5497, "net_load_act": null, "hsl_outage": 4288.0}, {"date": "2026-07-20", "he": 4, "load_fcst": 54656.02, "load_act": null, "solar_fcst": 0.0, "solar_act": null, "wind_fcst": 16500.1, "wind_act": null, "net_load_fcst": 38155.92, "net_load_act": null, "hsl_outage": 4288.0}, {"date": "2026-07-20", "he": 5, "load_fcst": 54205.6493, "load_act": null, "solar_fcst": 0.0, "solar_act": null, "wind_fcst": 15227.0, "wind_act": null, "net_load_fcst": 38978.6493, "net_load_act": null, "hsl_outage": 4288.0}, {"date": "2026-07-20", "he": 6, "load_fcst": 55005.8104, "load_act": null, "solar_fcst": 0.0, "solar_act": null, "wind_fcst": 13847.1, "wind_act": null, "net_load_fcst": 41158.7104, "net_load_act": null, "hsl_outage": 4288.0}, {"date": "2026-07-20", "he": 7, "load_fcst": 55970.7402, "load_act": null, "solar_fcst": 134.4, "solar_act": null, "wind_fcst": 12469.6, "wind_act": null, "net_load_fcst": 43366.7402, "net_load_act": null, "hsl_outage": 4288.0}, {"date": "2026-07-20", "he": 8, "load_fcst": 56981.9399, "load_act": null, "solar_fcst": 5601.5, "solar_act": null, "wind_fcst": 11544.7, "wind_act": null, "net_load_fcst": 39835.7399, "net_load_act": null, "hsl_outage": 4327.0}, {"date": "2026-07-20", "he": 9, "load_fcst": 60407.2699, "load_act": null, "solar_fcst": 19480.3, "solar_act": null, "wind_fcst": 11057.5, "wind_act": null, "net_load_fcst": 29869.469899999996, "net_load_act": null, "hsl_outage": 4327.0}, {"date": "2026-07-20", "he": 10, "load_fcst": 64757.1219, "load_act": null, "solar_fcst": 27730.7, "solar_act": null, "wind_fcst": 10549.7, "wind_act": null, "net_load_fcst": 26476.7219, "net_load_act": null, "hsl_outage": 4327.0}, {"date": "2026-07-20", "he": 11, "load_fcst": 69346.0508, "load_act": null, "solar_fcst": 31057.1, "solar_act": null, "wind_fcst": 10048.9, "wind_act": null, "net_load_fcst": 28240.050799999997, "net_load_act": null, "hsl_outage": 4327.0}, {"date": "2026-07-20", "he": 12, "load_fcst": 73680.3613, "load_act": null, "solar_fcst": 32837.6, "solar_act": null, "wind_fcst": 9533.9, "wind_act": null, "net_load_fcst": 31308.861300000004, "net_load_act": null, "hsl_outage": 4327.0}, {"date": "2026-07-20", "he": 13, "load_fcst": 77884.0188, "load_act": null, "solar_fcst": 33388.6, "solar_act": null, "wind_fcst": 9017.1, "wind_act": null, "net_load_fcst": 35478.31880000001, "net_load_act": null, "hsl_outage": 4327.0}, {"date": "2026-07-20", "he": 14, "load_fcst": 81341.3397, "load_act": null, "solar_fcst": 33483.1, "solar_act": null, "wind_fcst": 9708.5, "wind_act": null, "net_load_fcst": 38149.7397, "net_load_act": null, "hsl_outage": 4327.0}, {"date": "2026-07-20", "he": 15, "load_fcst": 83311.15950000001, "load_act": null, "solar_fcst": 33383.4, "solar_act": null, "wind_fcst": 10805.3, "wind_act": null, "net_load_fcst": 39122.45950000001, "net_load_act": null, "hsl_outage": 4327.0}, {"date": "2026-07-20", "he": 16, "load_fcst": 84162.7587, "load_act": null, "solar_fcst": 32833.7, "solar_act": null, "wind_fcst": 11901.5, "wind_act": null, "net_load_fcst": 39427.55870000001, "net_load_act": null, "hsl_outage": 4327.0}, {"date": "2026-07-20", "he": 17, "load_fcst": 84389.9807, "load_act": null, "solar_fcst": 32393.7, "solar_act": null, "wind_fcst": 12944.7, "wind_act": null, "net_load_fcst": 39051.580700000006, "net_load_act": null, "hsl_outage": 4327.0}, {"date": "2026-07-20", "he": 18, "load_fcst": 84169.6808, "load_act": null, "solar_fcst": 30763.2, "solar_act": null, "wind_fcst": 13914.0, "wind_act": null, "net_load_fcst": 39492.480800000005, "net_load_act": null, "hsl_outage": 4327.0}, {"date": "2026-07-20", "he": 19, "load_fcst": 83251.9092, "load_act": null, "solar_fcst": 25434.1, "solar_act": null, "wind_fcst": 15536.7, "wind_act": null, "net_load_fcst": 42281.10919999999, "net_load_act": null, "hsl_outage": 4319.0}, {"date": "2026-07-20", "he": 20, "load_fcst": 81346.4202, "load_act": null, "solar_fcst": 11827.5, "solar_act": null, "wind_fcst": 17164.1, "wind_act": null, "net_load_fcst": 52354.820199999995, "net_load_act": null, "hsl_outage": 4319.0}, {"date": "2026-07-20", "he": 21, "load_fcst": 78468.6286, "load_act": null, "solar_fcst": 1049.8, "solar_act": null, "wind_fcst": 17761.8, "wind_act": null, "net_load_fcst": 59657.02859999999, "net_load_act": null, "hsl_outage": 4291.0}, {"date": "2026-07-20", "he": 22, "load_fcst": 76077.5906, "load_act": null, "solar_fcst": 0.0, "solar_act": null, "wind_fcst": 18360.2, "wind_act": null, "net_load_fcst": 57717.3906, "net_load_act": null, "hsl_outage": 4291.0}, {"date": "2026-07-20", "he": 23, "load_fcst": 71874.1297, "load_act": null, "solar_fcst": 0.0, "solar_act": null, "wind_fcst": 18816.5, "wind_act": null, "net_load_fcst": 53057.629700000005, "net_load_act": null, "hsl_outage": 4291.0}, {"date": "2026-07-20", "he": 24, "load_fcst": 67443.1293, "load_act": null, "solar_fcst": 0.0, "solar_act": null, "wind_fcst": 19102.6, "wind_act": null, "net_load_fcst": 48340.5293, "net_load_act": null, "hsl_outage": 3894.0}, {"date": "2026-07-21", "he": 1, "load_fcst": 63164.9793, "load_act": null, "solar_fcst": 0.0, "solar_act": null, "wind_fcst": 19386.5, "wind_act": null, "net_load_fcst": 43778.4793, "net_load_act": null, "hsl_outage": 3894.0}, {"date": "2026-07-21", "he": 2, "load_fcst": 59787.0211, "load_act": null, "solar_fcst": 0.0, "solar_act": null, "wind_fcst": 19225.0, "wind_act": null, "net_load_fcst": 40562.0211, "net_load_act": null, "hsl_outage": 3894.0}, {"date": "2026-07-21", "he": 3, "load_fcst": 57123.1097, "load_act": null, "solar_fcst": 0.0, "solar_act": null, "wind_fcst": 16958.9, "wind_act": null, "net_load_fcst": 40164.2097, "net_load_act": null, "hsl_outage": 3894.0}, {"date": "2026-07-21", "he": 4, "load_fcst": 55687.2304, "load_act": null, "solar_fcst": 0.0, "solar_act": null, "wind_fcst": 15763.1, "wind_act": null, "net_load_fcst": 39924.1304, "net_load_act": null, "hsl_outage": 3894.0}, {"date": "2026-07-21", "he": 5, "load_fcst": 55185.7796, "load_act": null, "solar_fcst": 0.0, "solar_act": null, "wind_fcst": 14555.5, "wind_act": null, "net_load_fcst": 40630.2796, "net_load_act": null, "hsl_outage": 3894.0}, {"date": "2026-07-21", "he": 6, "load_fcst": 55984.7004, "load_act": null, "solar_fcst": 0.0, "solar_act": null, "wind_fcst": 13335.6, "wind_act": null, "net_load_fcst": 42649.1004, "net_load_act": null, "hsl_outage": 3894.0}, {"date": "2026-07-21", "he": 7, "load_fcst": 57085.8603, "load_act": null, "solar_fcst": 119.8, "solar_act": null, "wind_fcst": 11281.1, "wind_act": null, "net_load_fcst": 45684.9603, "net_load_act": null, "hsl_outage": 3894.0}, {"date": "2026-07-21", "he": 8, "load_fcst": 57895.828799999996, "load_act": null, "solar_fcst": 5144.1, "solar_act": null, "wind_fcst": 10411.9, "wind_act": null, "net_load_fcst": 42339.828799999996, "net_load_act": null, "hsl_outage": 3894.0}, {"date": "2026-07-21", "he": 9, "load_fcst": 60771.0084, "load_act": null, "solar_fcst": 18123.8, "solar_act": null, "wind_fcst": 10114.4, "wind_act": null, "net_load_fcst": 32532.8084, "net_load_act": null, "hsl_outage": 3904.0}, {"date": "2026-07-21", "he": 10, "load_fcst": 64862.72, "load_act": null, "solar_fcst": 25955.7, "solar_act": null, "wind_fcst": 9825.4, "wind_act": null, "net_load_fcst": 29081.620000000003, "net_load_act": null, "hsl_outage": 3904.0}, {"date": "2026-07-21", "he": 11, "load_fcst": 69372.6598, "load_act": null, "solar_fcst": 28768.2, "solar_act": null, "wind_fcst": 9615.3, "wind_act": null, "net_load_fcst": 30989.159799999998, "net_load_act": null, "hsl_outage": 3904.0}, {"date": "2026-07-21", "he": 12, "load_fcst": 73892.83009999999, "load_act": null, "solar_fcst": 30543.8, "solar_act": null, "wind_fcst": 9504.2, "wind_act": null, "net_load_fcst": 33844.83009999999, "net_load_act": null, "hsl_outage": 3904.0}, {"date": "2026-07-21", "he": 13, "load_fcst": 78255.8597, "load_act": null, "solar_fcst": 31300.3, "solar_act": null, "wind_fcst": 9397.5, "wind_act": null, "net_load_fcst": 37558.0597, "net_load_act": null, "hsl_outage": 3904.0}, {"date": "2026-07-21", "he": 14, "load_fcst": 81901.6209, "load_act": null, "solar_fcst": 31276.3, "solar_act": null, "wind_fcst": 8326.7, "wind_act": null, "net_load_fcst": 42298.620899999994, "net_load_act": null, "hsl_outage": 3904.0}, {"date": "2026-07-21", "he": 15, "load_fcst": 83753.0799, "load_act": null, "solar_fcst": 31067.8, "solar_act": null, "wind_fcst": 9303.7, "wind_act": null, "net_load_fcst": 43381.5799, "net_load_act": null, "hsl_outage": 3904.0}, {"date": "2026-07-21", "he": 16, "load_fcst": 84527.72, "load_act": null, "solar_fcst": 30333.1, "solar_act": null, "wind_fcst": 10300.2, "wind_act": null, "net_load_fcst": 43894.42, "net_load_act": null, "hsl_outage": 3904.0}, {"date": "2026-07-21", "he": 17, "load_fcst": 84676.9906, "load_act": null, "solar_fcst": 30039.6, "solar_act": null, "wind_fcst": 11265.1, "wind_act": null, "net_load_fcst": 43372.29060000001, "net_load_act": null, "hsl_outage": 3894.0}, {"date": "2026-07-21", "he": 18, "load_fcst": 84747.0989, "load_act": null, "solar_fcst": 28174.7, "solar_act": null, "wind_fcst": 12207.6, "wind_act": null, "net_load_fcst": 44364.7989, "net_load_act": null, "hsl_outage": 3894.0}, {"date": "2026-07-21", "he": 19, "load_fcst": 83966.54030000001, "load_act": null, "solar_fcst": 23037.8, "solar_act": null, "wind_fcst": 11832.5, "wind_act": null, "net_load_fcst": 49096.240300000005, "net_load_act": null, "hsl_outage": 3855.0}, {"date": "2026-07-21", "he": 20, "load_fcst": 82089.4299, "load_act": null, "solar_fcst": 10748.1, "solar_act": null, "wind_fcst": 12773.6, "wind_act": null, "net_load_fcst": 58567.7299, "net_load_act": null, "hsl_outage": 3855.0}, {"date": "2026-07-21", "he": 21, "load_fcst": 79241.5102, "load_act": null, "solar_fcst": 968.2, "solar_act": null, "wind_fcst": 13391.4, "wind_act": null, "net_load_fcst": 64881.910200000006, "net_load_act": null, "hsl_outage": 3855.0}, {"date": "2026-07-21", "he": 22, "load_fcst": 76814.2793, "load_act": null, "solar_fcst": 0.0, "solar_act": null, "wind_fcst": 13998.9, "wind_act": null, "net_load_fcst": 62815.37929999999, "net_load_act": null, "hsl_outage": 3855.0}, {"date": "2026-07-21", "he": 23, "load_fcst": 72707.59, "load_act": null, "solar_fcst": 0.0, "solar_act": null, "wind_fcst": 14340.6, "wind_act": null, "net_load_fcst": 58366.99, "net_load_act": null, "hsl_outage": 3855.0}, {"date": "2026-07-21", "he": 24, "load_fcst": 68359.5694, "load_act": null, "solar_fcst": 0.0, "solar_act": null, "wind_fcst": 14361.0, "wind_act": null, "net_load_fcst": 53998.56939999999, "net_load_act": null, "hsl_outage": 4156.0}, {"date": "2026-07-22", "he": 1, "load_fcst": 64134.7504, "load_act": null, "solar_fcst": 0.0, "solar_act": null, "wind_fcst": 14384.6, "wind_act": null, "net_load_fcst": 49750.1504, "net_load_act": null, "hsl_outage": 4156.0}, {"date": "2026-07-22", "he": 2, "load_fcst": 60657.4096, "load_act": null, "solar_fcst": 0.0, "solar_act": null, "wind_fcst": 15670.4, "wind_act": null, "net_load_fcst": 44987.0096, "net_load_act": null, "hsl_outage": 4156.0}, {"date": "2026-07-22", "he": 3, "load_fcst": 57958.7199, "load_act": null, "solar_fcst": 0.0, "solar_act": null, "wind_fcst": 14362.4, "wind_act": null, "net_load_fcst": 43596.319899999995, "net_load_act": null, "hsl_outage": 4156.0}, {"date": "2026-07-22", "he": 4, "load_fcst": 56380.99, "load_act": null, "solar_fcst": 0.0, "solar_act": null, "wind_fcst": 13060.1, "wind_act": null, "net_load_fcst": 43320.89, "net_load_act": null, "hsl_outage": 4156.0}, {"date": "2026-07-22", "he": 5, "load_fcst": 55769.5288, "load_act": null, "solar_fcst": 0.0, "solar_act": null, "wind_fcst": 11759.5, "wind_act": null, "net_load_fcst": 44010.0288, "net_load_act": null, "hsl_outage": 4156.0}, {"date": "2026-07-22", "he": 6, "load_fcst": 56427.609300000004, "load_act": null, "solar_fcst": 0.0, "solar_act": null, "wind_fcst": 10460.2, "wind_act": null, "net_load_fcst": 45967.4093, "net_load_act": null, "hsl_outage": 4156.0}, {"date": "2026-07-22", "he": 7, "load_fcst": 57344.610499999995, "load_act": null, "solar_fcst": 107.8, "solar_act": null, "wind_fcst": 10352.0, "wind_act": null, "net_load_fcst": 46884.81049999999, "net_load_act": null, "hsl_outage": 4156.0}, {"date": "2026-07-22", "he": 8, "load_fcst": 58138.1091, "load_act": null, "solar_fcst": 5122.6, "solar_act": null, "wind_fcst": 9663.6, "wind_act": null, "net_load_fcst": 43351.909100000004, "net_load_act": null, "hsl_outage": 4156.0}, {"date": "2026-07-22", "he": 9, "load_fcst": 61113.2197, "load_act": null, "solar_fcst": 18598.6, "solar_act": null, "wind_fcst": 8996.6, "wind_act": null, "net_load_fcst": 33518.019700000004, "net_load_act": null, "hsl_outage": 4156.0}, {"date": "2026-07-22", "he": 10, "load_fcst": 65567.7902, "load_act": null, "solar_fcst": 26814.7, "solar_act": null, "wind_fcst": 8329.9, "wind_act": null, "net_load_fcst": 30423.190200000005, "net_load_act": null, "hsl_outage": 4156.0}, {"date": "2026-07-22", "he": 11, "load_fcst": 70459.559, "load_act": null, "solar_fcst": 30475.5, "solar_act": null, "wind_fcst": 7648.1, "wind_act": null, "net_load_fcst": 32335.958999999995, "net_load_act": null, "hsl_outage": 3856.0}, {"date": "2026-07-22", "he": 12, "load_fcst": 75206.4506, "load_act": null, "solar_fcst": 32332.0, "solar_act": null, "wind_fcst": 6947.9, "wind_act": null, "net_load_fcst": 35926.550599999995, "net_load_act": null, "hsl_outage": 3856.0}, {"date": "2026-07-22", "he": 13, "load_fcst": 79392.0993, "load_act": null, "solar_fcst": 33117.7, "solar_act": null, "wind_fcst": 7038.7, "wind_act": null, "net_load_fcst": 39235.69930000001, "net_load_act": null, "hsl_outage": 3856.0}, {"date": "2026-07-22", "he": 14, "load_fcst": 82934.0707, "load_act": null, "solar_fcst": 33549.1, "solar_act": null, "wind_fcst": 7221.9, "wind_act": null, "net_load_fcst": 42163.0707, "net_load_act": null, "hsl_outage": 3856.0}, {"date": "2026-07-22", "he": 15, "load_fcst": 84651.8985, "load_act": null, "solar_fcst": 33506.6, "solar_act": null, "wind_fcst": 8435.7, "wind_act": null, "net_load_fcst": 42709.59849999999, "net_load_act": null, "hsl_outage": 3856.0}, {"date": "2026-07-22", "he": 16, "load_fcst": 85551.4503, "load_act": null, "solar_fcst": null, "solar_act": null, "wind_fcst": null, "wind_act": null, "net_load_fcst": null, "net_load_act": null, "hsl_outage": 3856.0}, {"date": "2026-07-22", "he": 17, "load_fcst": 85724.3602, "load_act": null, "solar_fcst": null, "solar_act": null, "wind_fcst": null, "wind_act": null, "net_load_fcst": null, "net_load_act": null, "hsl_outage": 3856.0}, {"date": "2026-07-22", "he": 18, "load_fcst": 85713.6206, "load_act": null, "solar_fcst": null, "solar_act": null, "wind_fcst": null, "wind_act": null, "net_load_fcst": null, "net_load_act": null, "hsl_outage": 3856.0}, {"date": "2026-07-22", "he": 19, "load_fcst": 84720.6792, "load_act": null, "solar_fcst": null, "solar_act": null, "wind_fcst": null, "wind_act": null, "net_load_fcst": null, "net_load_act": null, "hsl_outage": 3856.0}, {"date": "2026-07-22", "he": 20, "load_fcst": 82549.1884, "load_act": null, "solar_fcst": null, "solar_act": null, "wind_fcst": null, "wind_act": null, "net_load_fcst": null, "net_load_act": null, "hsl_outage": 3856.0}, {"date": "2026-07-22", "he": 21, "load_fcst": 79480.3195, "load_act": null, "solar_fcst": null, "solar_act": null, "wind_fcst": null, "wind_act": null, "net_load_fcst": null, "net_load_act": null, "hsl_outage": 3856.0}, {"date": "2026-07-22", "he": 22, "load_fcst": 76904.32949999999, "load_act": null, "solar_fcst": null, "solar_act": null, "wind_fcst": null, "wind_act": null, "net_load_fcst": null, "net_load_act": null, "hsl_outage": 3856.0}, {"date": "2026-07-22", "he": 23, "load_fcst": 72791.3105, "load_act": null, "solar_fcst": null, "solar_act": null, "wind_fcst": null, "wind_act": null, "net_load_fcst": null, "net_load_act": null, "hsl_outage": 3856.0}, {"date": "2026-07-22", "he": 24, "load_fcst": 68330.4195, "load_act": null, "solar_fcst": null, "solar_act": null, "wind_fcst": null, "wind_act": null, "net_load_fcst": null, "net_load_act": null, "hsl_outage": null}]}