{"generated_at": "2026-07-22 10:48 CDT", "now_date": "2026-07-22", "now_he": 11, "points": [{"date": "2026-07-21", "he": 1, "load_fcst": 65513.4704, "load_act": 65220.74, "solar_fcst": 0.0, "solar_act": 0.07, "wind_fcst": 19386.5, "wind_act": 17472.75, "net_load_fcst": 46126.9704, "net_load_act": 47747.92, "hsl_outage": 7140.0}, {"date": "2026-07-21", "he": 2, "load_fcst": 61915.0891, "load_act": 61855.31, "solar_fcst": 0.0, "solar_act": 0.09, "wind_fcst": 19225.0, "wind_act": 17049.13, "net_load_fcst": 42690.0891, "net_load_act": 44806.09, "hsl_outage": 7122.0}, {"date": "2026-07-21", "he": 3, "load_fcst": 59181.0795, "load_act": 59312.63, "solar_fcst": 0.0, "solar_act": 0.1, "wind_fcst": 16958.9, "wind_act": 15679.0, "net_load_fcst": 42222.1795, "net_load_act": 43633.53, "hsl_outage": 7122.0}, {"date": "2026-07-21", "he": 4, "load_fcst": 57552.9209, "load_act": 57461.72, "solar_fcst": 0.0, "solar_act": 0.1, "wind_fcst": 15763.1, "wind_act": 13876.69, "net_load_fcst": 41789.8209, "net_load_act": 43584.93, "hsl_outage": 7086.0}, {"date": "2026-07-21", "he": 5, "load_fcst": 56587.259900000005, "load_act": 56578.57, "solar_fcst": 0.0, "solar_act": 0.11, "wind_fcst": 14555.5, "wind_act": 11532.56, "net_load_fcst": 42031.759900000005, "net_load_act": 45045.9, "hsl_outage": 7086.0}, {"date": "2026-07-21", "he": 6, "load_fcst": 56766.3696, "load_act": 56852.24, "solar_fcst": 0.0, "solar_act": 0.12, "wind_fcst": 13335.6, "wind_act": 9492.73, "net_load_fcst": 43430.7696, "net_load_act": 47359.39, "hsl_outage": 7096.0}, {"date": "2026-07-21", "he": 7, "load_fcst": 57504.2002, "load_act": 57870.86, "solar_fcst": 119.8, "solar_act": 72.73, "wind_fcst": 11281.1, "wind_act": 7286.53, "net_load_fcst": 46103.3002, "net_load_act": 50511.6, "hsl_outage": 7126.0}, {"date": "2026-07-21", "he": 8, "load_fcst": 58741.4994, "load_act": 58668.68, "solar_fcst": 5144.1, "solar_act": 5392.3, "wind_fcst": 10411.9, "wind_act": 5835.48, "net_load_fcst": 43185.4994, "net_load_act": 47440.899999999994, "hsl_outage": 7126.0}, {"date": "2026-07-21", "he": 9, "load_fcst": 61302.1005, "load_act": 61063.91, "solar_fcst": 18123.8, "solar_act": 20754.25, "wind_fcst": 10114.4, "wind_act": 3725.42, "net_load_fcst": 33063.900499999996, "net_load_act": 36584.240000000005, "hsl_outage": 7441.0}, {"date": "2026-07-21", "he": 10, "load_fcst": 64481.8105, "load_act": 64862.47, "solar_fcst": 25955.7, "solar_act": 30164.02, "wind_fcst": 9825.4, "wind_act": 2161.13, "net_load_fcst": 28700.710499999994, "net_load_act": 32537.319999999996, "hsl_outage": 7441.0}, {"date": "2026-07-21", "he": 11, "load_fcst": 69405.5399, "load_act": 69589.19, "solar_fcst": 28768.2, "solar_act": 33657.28, "wind_fcst": 9615.3, "wind_act": 1554.01, "net_load_fcst": 31022.039900000007, "net_load_act": 34377.9, "hsl_outage": 7437.0}, {"date": "2026-07-21", "he": 12, "load_fcst": 74361.64020000001, "load_act": 74729.95, "solar_fcst": 30543.8, "solar_act": 34374.71, "wind_fcst": 9504.2, "wind_act": 1381.87, "net_load_fcst": 34313.64020000001, "net_load_act": 38973.369999999995, "hsl_outage": 7313.0}, {"date": "2026-07-21", "he": 13, "load_fcst": 79631.1104, "load_act": 79724.68, "solar_fcst": 31300.3, "solar_act": 34225.9, "wind_fcst": 9397.5, "wind_act": 1287.9, "net_load_fcst": 38933.3104, "net_load_act": 44210.87999999999, "hsl_outage": 7308.0}, {"date": "2026-07-21", "he": 14, "load_fcst": 84194.7206, "load_act": 83923.77, "solar_fcst": 31276.3, "solar_act": 34079.41, "wind_fcst": 8326.7, "wind_act": 1399.46, "net_load_fcst": 44591.7206, "net_load_act": 48444.9, "hsl_outage": 7298.0}, {"date": "2026-07-21", "he": 15, "load_fcst": 86719.0616, "load_act": 85312.48, "solar_fcst": 31067.8, "solar_act": 33595.08, "wind_fcst": 9303.7, "wind_act": 1950.16, "net_load_fcst": 46347.5616, "net_load_act": 49767.23999999999, "hsl_outage": 7275.0}, {"date": "2026-07-21", "he": 16, "load_fcst": 85695.5793, "load_act": 86116.93, "solar_fcst": 30333.1, "solar_act": 32636.92, "wind_fcst": 10300.2, "wind_act": 2760.0, "net_load_fcst": 45062.279299999995, "net_load_act": 50720.009999999995, "hsl_outage": 7295.0}, {"date": "2026-07-21", "he": 17, "load_fcst": 86428.2795, "load_act": 87014.9, "solar_fcst": 30039.6, "solar_act": 31988.73, "wind_fcst": 11265.1, "wind_act": 3501.88, "net_load_fcst": 45123.57950000001, "net_load_act": 51524.29, "hsl_outage": 7285.0}, {"date": "2026-07-21", "he": 18, "load_fcst": 87502.6807, "load_act": 87403.19, "solar_fcst": 28174.7, "solar_act": 30261.43, "wind_fcst": 12207.6, "wind_act": 3949.43, "net_load_fcst": 47120.3807, "net_load_act": 53192.33, "hsl_outage": 7065.0}, {"date": "2026-07-21", "he": 19, "load_fcst": 86742.5291, "load_act": 86965.61, "solar_fcst": 23037.8, "solar_act": 24589.96, "wind_fcst": 11832.5, "wind_act": 4316.9, "net_load_fcst": 51872.2291, "net_load_act": 58058.75, "hsl_outage": 6895.0}, {"date": "2026-07-21", "he": 20, "load_fcst": 85356.3302, "load_act": 85043.84, "solar_fcst": 10748.1, "solar_act": 11129.67, "wind_fcst": 12773.6, "wind_act": 4823.72, "net_load_fcst": 61834.63019999999, "net_load_act": 69090.45, "hsl_outage": 6895.0}, {"date": "2026-07-21", "he": 21, "load_fcst": 81576.6404, "load_act": 81568.2, "solar_fcst": 968.2, "solar_act": 906.85, "wind_fcst": 13391.4, "wind_act": 6396.84, "net_load_fcst": 67217.04040000001, "net_load_act": 74264.51, "hsl_outage": 6895.0}, {"date": "2026-07-21", "he": 22, "load_fcst": 79237.8008, "load_act": 79065.15, "solar_fcst": 0.0, "solar_act": 0.23, "wind_fcst": 13998.9, "wind_act": 7882.97, "net_load_fcst": 65238.900799999996, "net_load_act": 71181.95, "hsl_outage": 6895.0}, {"date": "2026-07-21", "he": 23, "load_fcst": 75642.2704, "load_act": 74919.43, "solar_fcst": 0.0, "solar_act": 0.7, "wind_fcst": 14340.6, "wind_act": 8336.43, "net_load_fcst": 61301.670399999995, "net_load_act": 66582.29999999999, "hsl_outage": 6895.0}, {"date": "2026-07-21", "he": 24, "load_fcst": 71845.4497, "load_act": 71243.75, "solar_fcst": 0.0, "solar_act": 1.11, "wind_fcst": 14361.0, "wind_act": 8951.26, "net_load_fcst": 57484.4497, "net_load_act": 62291.38, "hsl_outage": 6310.0}, {"date": "2026-07-22", "he": 1, "load_fcst": 67978.4895, "load_act": null, "solar_fcst": 0.0, "solar_act": 0.35, "wind_fcst": 14384.6, "wind_act": 9112.47, "net_load_fcst": 53593.8895, "net_load_act": null, "hsl_outage": 6310.0}, {"date": "2026-07-22", "he": 2, "load_fcst": 64597.5005, "load_act": null, "solar_fcst": 0.0, "solar_act": 0.08, "wind_fcst": 15670.4, "wind_act": 8889.12, "net_load_fcst": 48927.1005, "net_load_act": null, "hsl_outage": 6310.0}, {"date": "2026-07-22", "he": 3, "load_fcst": 62095.5909, "load_act": null, "solar_fcst": 0.0, "solar_act": 0.11, "wind_fcst": 14362.4, "wind_act": 8197.6, "net_load_fcst": 47733.1909, "net_load_act": null, "hsl_outage": 6310.0}, {"date": "2026-07-22", "he": 4, "load_fcst": 60183.8091, "load_act": null, "solar_fcst": 0.0, "solar_act": 0.27, "wind_fcst": 13060.1, "wind_act": 6842.12, "net_load_fcst": 47123.7091, "net_load_act": null, "hsl_outage": 6710.0}, {"date": "2026-07-22", "he": 5, "load_fcst": 59222.9194, "load_act": null, "solar_fcst": 0.0, "solar_act": 0.39, "wind_fcst": 11759.5, "wind_act": 5855.11, "net_load_fcst": 47463.4194, "net_load_act": null, "hsl_outage": 6710.0}, {"date": "2026-07-22", "he": 6, "load_fcst": 59622.7898, "load_act": null, "solar_fcst": 0.0, "solar_act": 0.48, "wind_fcst": 10460.2, "wind_act": 4658.57, "net_load_fcst": 49162.5898, "net_load_act": null, "hsl_outage": 6310.0}, {"date": "2026-07-22", "he": 7, "load_fcst": 59985.7186, "load_act": null, "solar_fcst": 107.8, "solar_act": 68.43, "wind_fcst": 10352.0, "wind_act": 3604.57, "net_load_fcst": 49525.9186, "net_load_act": null, "hsl_outage": 6310.0}, {"date": "2026-07-22", "he": 8, "load_fcst": 60690.1406, "load_act": null, "solar_fcst": 5122.6, "solar_act": 5623.34, "wind_fcst": 9663.6, "wind_act": 2709.33, "net_load_fcst": 45903.9406, "net_load_act": null, "hsl_outage": 6310.0}, {"date": "2026-07-22", "he": 9, "load_fcst": 63456.6201, "load_act": null, "solar_fcst": 18598.6, "solar_act": 20869.95, "wind_fcst": 8996.6, "wind_act": 1304.77, "net_load_fcst": 35861.4201, "net_load_act": null, "hsl_outage": 6310.0}, {"date": "2026-07-22", "he": 10, "load_fcst": 68256.8581, "load_act": null, "solar_fcst": 26814.7, "solar_act": null, "wind_fcst": 8329.9, "wind_act": null, "net_load_fcst": 33112.2581, "net_load_act": null, "hsl_outage": 6460.0}, {"date": "2026-07-22", "he": 11, "load_fcst": 73787.5204, "load_act": null, "solar_fcst": 30475.5, "solar_act": null, "wind_fcst": 7648.1, "wind_act": null, "net_load_fcst": 35663.920399999995, "net_load_act": null, "hsl_outage": 6170.0}, {"date": "2026-07-22", "he": 12, "load_fcst": 79116.548, "load_act": null, "solar_fcst": 32332.0, "solar_act": null, "wind_fcst": 6947.9, "wind_act": null, "net_load_fcst": 39836.647999999994, "net_load_act": null, "hsl_outage": 6237.0}, {"date": "2026-07-22", "he": 13, "load_fcst": 84017.7983, "load_act": null, "solar_fcst": 33117.7, "solar_act": null, "wind_fcst": 7038.7, "wind_act": null, "net_load_fcst": 43861.3983, "net_load_act": null, "hsl_outage": 5910.0}, {"date": "2026-07-22", "he": 14, "load_fcst": 88194.5603, "load_act": null, "solar_fcst": 33549.1, "solar_act": null, "wind_fcst": 7221.9, "wind_act": null, "net_load_fcst": 47423.5603, "net_load_act": null, "hsl_outage": 5910.0}, {"date": "2026-07-22", "he": 15, "load_fcst": 89847.9305, "load_act": null, "solar_fcst": 33506.6, "solar_act": null, "wind_fcst": 8435.7, "wind_act": null, "net_load_fcst": 47905.6305, "net_load_act": null, "hsl_outage": 5518.0}, {"date": "2026-07-22", "he": 16, "load_fcst": 90093.9299, "load_act": null, "solar_fcst": 33043.2, "solar_act": null, "wind_fcst": 9850.1, "wind_act": null, "net_load_fcst": 47200.62990000001, "net_load_act": null, "hsl_outage": 5518.0}, {"date": "2026-07-22", "he": 17, "load_fcst": 89313.20939999999, "load_act": null, "solar_fcst": 33224.6, "solar_act": null, "wind_fcst": 11344.4, "wind_act": null, "net_load_fcst": 44744.20939999999, "net_load_act": null, "hsl_outage": 5451.0}, {"date": "2026-07-22", "he": 18, "load_fcst": 88562.9296, "load_act": null, "solar_fcst": 31885.8, "solar_act": null, "wind_fcst": 12941.3, "wind_act": null, "net_load_fcst": 43735.8296, "net_load_act": null, "hsl_outage": 5361.0}, {"date": "2026-07-22", "he": 19, "load_fcst": 87828.4595, "load_act": null, "solar_fcst": 26570.3, "solar_act": null, "wind_fcst": 13709.0, "wind_act": null, "net_load_fcst": 47549.159499999994, "net_load_act": null, "hsl_outage": 5358.0}, {"date": "2026-07-22", "he": 20, "load_fcst": 86665.2196, "load_act": null, "solar_fcst": 12274.1, "solar_act": null, "wind_fcst": 15069.0, "wind_act": null, "net_load_fcst": 59322.11959999999, "net_load_act": null, "hsl_outage": 5328.0}, {"date": "2026-07-22", "he": 21, "load_fcst": 83941.561, "load_act": null, "solar_fcst": 1071.9, "solar_act": null, "wind_fcst": 16309.7, "wind_act": null, "net_load_fcst": 66559.96100000001, "net_load_act": null, "hsl_outage": 5328.0}, {"date": "2026-07-22", "he": 22, "load_fcst": 81649.5802, "load_act": null, "solar_fcst": 0.0, "solar_act": null, "wind_fcst": 17516.1, "wind_act": null, "net_load_fcst": 64133.4802, "net_load_act": null, "hsl_outage": 5308.0}, {"date": "2026-07-22", "he": 23, "load_fcst": 77616.36929999999, "load_act": null, "solar_fcst": 0.0, "solar_act": null, "wind_fcst": 18440.0, "wind_act": null, "net_load_fcst": 59176.36929999999, "net_load_act": null, "hsl_outage": 5308.0}, {"date": "2026-07-22", "he": 24, "load_fcst": 73128.2484, "load_act": null, "solar_fcst": 0.0, "solar_act": null, "wind_fcst": 19007.0, "wind_act": null, "net_load_fcst": 54121.2484, "net_load_act": null, "hsl_outage": 5231.0}, {"date": "2026-07-23", "he": 1, "load_fcst": 69709.4997, "load_act": null, "solar_fcst": 0.0, "solar_act": null, "wind_fcst": 19064.5, "wind_act": null, "net_load_fcst": 50644.9997, "net_load_act": null, "hsl_outage": 5231.0}, {"date": "2026-07-23", "he": 2, "load_fcst": 66249.689, "load_act": null, "solar_fcst": 0.0, "solar_act": null, "wind_fcst": 18934.8, "wind_act": null, "net_load_fcst": 47314.888999999996, "net_load_act": null, "hsl_outage": 5231.0}, {"date": "2026-07-23", "he": 3, "load_fcst": 63519.54, "load_act": null, "solar_fcst": 0.0, "solar_act": null, "wind_fcst": 17534.1, "wind_act": null, "net_load_fcst": 45985.44, "net_load_act": null, "hsl_outage": 5231.0}, {"date": "2026-07-23", "he": 4, "load_fcst": 61674.2005, "load_act": null, "solar_fcst": 0.0, "solar_act": null, "wind_fcst": 16452.5, "wind_act": null, "net_load_fcst": 45221.7005, "net_load_act": null, "hsl_outage": 5231.0}, {"date": "2026-07-23", "he": 5, "load_fcst": 60728.7199, "load_act": null, "solar_fcst": 0.0, "solar_act": null, "wind_fcst": 15270.6, "wind_act": null, "net_load_fcst": 45458.1199, "net_load_act": null, "hsl_outage": 5231.0}, {"date": "2026-07-23", "he": 6, "load_fcst": 61156.579, "load_act": null, "solar_fcst": 0.0, "solar_act": null, "wind_fcst": 13969.2, "wind_act": null, "net_load_fcst": 47187.379, "net_load_act": null, "hsl_outage": 5231.0}, {"date": "2026-07-23", "he": 7, "load_fcst": 61519.1506, "load_act": null, "solar_fcst": 109.5, "solar_act": null, "wind_fcst": 11819.6, "wind_act": null, "net_load_fcst": 49590.0506, "net_load_act": null, "hsl_outage": 4841.0}, {"date": "2026-07-23", "he": 8, "load_fcst": 61981.6999, "load_act": null, "solar_fcst": 5500.4, "solar_act": null, "wind_fcst": 10341.0, "wind_act": null, "net_load_fcst": 46140.2999, "net_load_act": null, "hsl_outage": 4841.0}, {"date": "2026-07-23", "he": 9, "load_fcst": 64615.0195, "load_act": null, "solar_fcst": 20101.7, "solar_act": null, "wind_fcst": 9088.7, "wind_act": null, "net_load_fcst": 35424.6195, "net_load_act": null, "hsl_outage": 4841.0}, {"date": "2026-07-23", "he": 10, "load_fcst": 68480.1299, "load_act": null, "solar_fcst": 28744.0, "solar_act": null, "wind_fcst": 7838.4, "wind_act": null, "net_load_fcst": 31897.7299, "net_load_act": null, "hsl_outage": 4789.0}, {"date": "2026-07-23", "he": 11, "load_fcst": 72825.1403, "load_act": null, "solar_fcst": 31689.5, "solar_act": null, "wind_fcst": 6733.5, "wind_act": null, "net_load_fcst": 34402.1403, "net_load_act": null, "hsl_outage": 4789.0}, {"date": "2026-07-23", "he": 12, "load_fcst": 76804.7602, "load_act": null, "solar_fcst": 33092.9, "solar_act": null, "wind_fcst": 5809.0, "wind_act": null, "net_load_fcst": 37902.8602, "net_load_act": null, "hsl_outage": 4901.0}, {"date": "2026-07-23", "he": 13, "load_fcst": 80529.2215, "load_act": null, "solar_fcst": 33573.1, "solar_act": null, "wind_fcst": 4884.0, "wind_act": null, "net_load_fcst": 42072.1215, "net_load_act": null, "hsl_outage": 4901.0}, {"date": "2026-07-23", "he": 14, "load_fcst": 83853.56109999999, "load_act": null, "solar_fcst": 34038.8, "solar_act": null, "wind_fcst": 4409.4, "wind_act": null, "net_load_fcst": 45405.36109999999, "net_load_act": null, "hsl_outage": 4901.0}, {"date": "2026-07-23", "he": 15, "load_fcst": 85625.5502, "load_act": null, "solar_fcst": 33853.6, "solar_act": null, "wind_fcst": 5753.1, "wind_act": null, "net_load_fcst": 46018.8502, "net_load_act": null, "hsl_outage": 4901.0}, {"date": "2026-07-23", "he": 16, "load_fcst": 86293.981, "load_act": null, "solar_fcst": 33468.3, "solar_act": null, "wind_fcst": 7095.9, "wind_act": null, "net_load_fcst": 45729.780999999995, "net_load_act": null, "hsl_outage": 4901.0}, {"date": "2026-07-23", "he": 17, "load_fcst": 86441.0989, "load_act": null, "solar_fcst": 33808.2, "solar_act": null, "wind_fcst": 8560.1, "wind_act": null, "net_load_fcst": 44072.7989, "net_load_act": null, "hsl_outage": 4789.0}, {"date": "2026-07-23", "he": 18, "load_fcst": 86289.7199, "load_act": null, "solar_fcst": 32433.2, "solar_act": null, "wind_fcst": 10171.2, "wind_act": null, "net_load_fcst": 43685.3199, "net_load_act": null, "hsl_outage": 4785.0}, {"date": "2026-07-23", "he": 19, "load_fcst": 85705.0095, "load_act": null, "solar_fcst": 26868.8, "solar_act": null, "wind_fcst": 11874.9, "wind_act": null, "net_load_fcst": 46961.309499999996, "net_load_act": null, "hsl_outage": 4785.0}, {"date": "2026-07-23", "he": 20, "load_fcst": 84279.75, "load_act": null, "solar_fcst": 11953.8, "solar_act": null, "wind_fcst": 13620.0, "wind_act": null, "net_load_fcst": 58705.95, "net_load_act": null, "hsl_outage": 4785.0}, {"date": "2026-07-23", "he": 21, "load_fcst": 81741.2496, "load_act": null, "solar_fcst": 985.3, "solar_act": null, "wind_fcst": 15115.0, "wind_act": null, "net_load_fcst": 65640.94959999999, "net_load_act": null, "hsl_outage": 4785.0}, {"date": "2026-07-23", "he": 22, "load_fcst": 79541.1007, "load_act": null, "solar_fcst": 0.0, "solar_act": null, "wind_fcst": 16556.9, "wind_act": null, "net_load_fcst": 62984.200699999994, "net_load_act": null, "hsl_outage": 4785.0}, {"date": "2026-07-23", "he": 23, "load_fcst": 75797.5794, "load_act": null, "solar_fcst": 0.0, "solar_act": null, "wind_fcst": 17745.2, "wind_act": null, "net_load_fcst": 58052.379400000005, "net_load_act": null, "hsl_outage": 4785.0}, {"date": "2026-07-23", "he": 24, "load_fcst": 71707.4111, "load_act": null, "solar_fcst": 0.0, "solar_act": null, "wind_fcst": 18623.8, "wind_act": null, "net_load_fcst": 53083.611099999995, "net_load_act": null, "hsl_outage": 4785.0}, {"date": "2026-07-24", "he": 1, "load_fcst": 67174.3173, "load_act": null, "solar_fcst": 0.0, "solar_act": null, "wind_fcst": 19540.9, "wind_act": null, "net_load_fcst": 47633.417299999994, "net_load_act": null, "hsl_outage": 4785.0}, {"date": "2026-07-24", "he": 2, "load_fcst": 64009.7115, "load_act": null, "solar_fcst": 0.0, "solar_act": null, "wind_fcst": 19798.0, "wind_act": null, "net_load_fcst": 44211.7115, "net_load_act": null, "hsl_outage": 4785.0}, {"date": "2026-07-24", "he": 3, "load_fcst": 61508.2316, "load_act": null, "solar_fcst": 0.0, "solar_act": null, "wind_fcst": 18791.5, "wind_act": null, "net_load_fcst": 42716.7316, "net_load_act": null, "hsl_outage": 4785.0}, {"date": "2026-07-24", "he": 4, "load_fcst": 59721.8273, "load_act": null, "solar_fcst": 0.0, "solar_act": null, "wind_fcst": 17785.7, "wind_act": null, "net_load_fcst": 41936.12729999999, "net_load_act": null, "hsl_outage": 4785.0}, {"date": "2026-07-24", "he": 5, "load_fcst": 58963.7029, "load_act": null, "solar_fcst": 0.0, "solar_act": null, "wind_fcst": 16678.5, "wind_act": null, "net_load_fcst": 42285.2029, "net_load_act": null, "hsl_outage": 4785.0}, {"date": "2026-07-24", "he": 6, "load_fcst": 59095.7005, "load_act": null, "solar_fcst": 0.0, "solar_act": null, "wind_fcst": 15451.7, "wind_act": null, "net_load_fcst": 43644.000499999995, "net_load_act": null, "hsl_outage": 4785.0}, {"date": "2026-07-24", "he": 7, "load_fcst": 59698.536700000004, "load_act": null, "solar_fcst": 100.4, "solar_act": null, "wind_fcst": 14511.7, "wind_act": null, "net_load_fcst": 45086.436700000006, "net_load_act": null, "hsl_outage": 4785.0}, {"date": "2026-07-24", "he": 8, "load_fcst": 60543.3848, "load_act": null, "solar_fcst": 5267.7, "solar_act": null, "wind_fcst": 13245.5, "wind_act": null, "net_load_fcst": 42030.1848, "net_load_act": null, "hsl_outage": 4785.0}, {"date": "2026-07-24", "he": 9, "load_fcst": 63292.8648, "load_act": null, "solar_fcst": 19589.8, "solar_act": null, "wind_fcst": 11911.5, "wind_act": null, "net_load_fcst": 31791.564800000007, "net_load_act": null, "hsl_outage": 4785.0}, {"date": "2026-07-24", "he": 10, "load_fcst": 67465.2711, "load_act": null, "solar_fcst": 28405.6, "solar_act": null, "wind_fcst": 10577.1, "wind_act": null, "net_load_fcst": 28482.5711, "net_load_act": null, "hsl_outage": 4885.0}, {"date": "2026-07-24", "he": 11, "load_fcst": 71887.4199, "load_act": null, "solar_fcst": 31293.0, "solar_act": null, "wind_fcst": 9237.8, "wind_act": null, "net_load_fcst": 31356.619899999994, "net_load_act": null, "hsl_outage": 4885.0}, {"date": "2026-07-24", "he": 12, "load_fcst": 76278.1129, "load_act": null, "solar_fcst": 32684.7, "solar_act": null, "wind_fcst": 7897.4, "wind_act": null, "net_load_fcst": 35696.012899999994, "net_load_act": null, "hsl_outage": 5006.0}, {"date": "2026-07-24", "he": 13, "load_fcst": 80093.8038, "load_act": null, "solar_fcst": 33373.7, "solar_act": null, "wind_fcst": 6553.9, "wind_act": null, "net_load_fcst": 40166.203799999996, "net_load_act": null, "hsl_outage": 5000.0}, {"date": "2026-07-24", "he": 14, "load_fcst": 83266.3132, "load_act": null, "solar_fcst": 33667.6, "solar_act": null, "wind_fcst": 8118.7, "wind_act": null, "net_load_fcst": 41480.01320000001, "net_load_act": null, "hsl_outage": 5000.0}, {"date": "2026-07-24", "he": 15, "load_fcst": 84917.689, "load_act": null, "solar_fcst": 33537.5, "solar_act": null, "wind_fcst": 9607.8, "wind_act": null, "net_load_fcst": 41772.388999999996, "net_load_act": null, "hsl_outage": 4900.0}, {"date": "2026-07-24", "he": 16, "load_fcst": 85490.8527, "load_act": null, "solar_fcst": 32972.4, "solar_act": null, "wind_fcst": 11098.0, "wind_act": null, "net_load_fcst": 41420.4527, "net_load_act": null, "hsl_outage": 4900.0}, {"date": "2026-07-24", "he": 17, "load_fcst": 85600.3301, "load_act": null, "solar_fcst": 32838.3, "solar_act": null, "wind_fcst": 12823.3, "wind_act": null, "net_load_fcst": 39938.7301, "net_load_act": null, "hsl_outage": 4779.0}, {"date": "2026-07-24", "he": 18, "load_fcst": 85214.6748, "load_act": null, "solar_fcst": 31352.1, "solar_act": null, "wind_fcst": 14829.9, "wind_act": null, "net_load_fcst": 39032.67479999999, "net_load_act": null, "hsl_outage": 4779.0}, {"date": "2026-07-24", "he": 19, "load_fcst": 84329.8931, "load_act": null, "solar_fcst": 25935.5, "solar_act": null, "wind_fcst": 17188.8, "wind_act": null, "net_load_fcst": 41205.5931, "net_load_act": null, "hsl_outage": 4753.0}, {"date": "2026-07-24", "he": 20, "load_fcst": 82475.6282, "load_act": null, "solar_fcst": 11724.3, "solar_act": null, "wind_fcst": 19243.6, "wind_act": null, "net_load_fcst": 51507.728200000005, "net_load_act": null, "hsl_outage": 4603.0}, {"date": "2026-07-24", "he": 21, "load_fcst": 79710.9431, "load_act": null, "solar_fcst": 1002.8, "solar_act": null, "wind_fcst": 20252.1, "wind_act": null, "net_load_fcst": 58456.0431, "net_load_act": null, "hsl_outage": 4603.0}, {"date": "2026-07-24", "he": 22, "load_fcst": 77758.9342, "load_act": null, "solar_fcst": 0.0, "solar_act": null, "wind_fcst": 21259.5, "wind_act": null, "net_load_fcst": 56499.4342, "net_load_act": null, "hsl_outage": 4603.0}, {"date": "2026-07-24", "he": 23, "load_fcst": 74475.5223, "load_act": null, "solar_fcst": 0.0, "solar_act": null, "wind_fcst": 21931.4, "wind_act": null, "net_load_fcst": 52544.122299999995, "net_load_act": null, "hsl_outage": 4603.0}, {"date": "2026-07-24", "he": 24, "load_fcst": 70664.1279, "load_act": null, "solar_fcst": 0.0, "solar_act": null, "wind_fcst": 22146.7, "wind_act": null, "net_load_fcst": 48517.42790000001, "net_load_act": null, "hsl_outage": 4373.0}, {"date": "2026-07-25", "he": 1, "load_fcst": 67001.6445, "load_act": null, "solar_fcst": 0.0, "solar_act": null, "wind_fcst": 22441.8, "wind_act": null, "net_load_fcst": 44559.84449999999, "net_load_act": null, "hsl_outage": 4373.0}, {"date": "2026-07-25", "he": 2, "load_fcst": 63657.0001, "load_act": null, "solar_fcst": 0.0, "solar_act": null, "wind_fcst": 22393.8, "wind_act": null, "net_load_fcst": 41263.2001, "net_load_act": null, "hsl_outage": 4373.0}, {"date": "2026-07-25", "he": 3, "load_fcst": 61093.4518, "load_act": null, "solar_fcst": 0.0, "solar_act": null, "wind_fcst": 21547.6, "wind_act": null, "net_load_fcst": 39545.851800000004, "net_load_act": null, "hsl_outage": 4373.0}, {"date": "2026-07-25", "he": 4, "load_fcst": 59067.8536, "load_act": null, "solar_fcst": 0.0, "solar_act": null, "wind_fcst": 20702.3, "wind_act": null, "net_load_fcst": 38365.5536, "net_load_act": null, "hsl_outage": 4373.0}, {"date": "2026-07-25", "he": 5, "load_fcst": 57749.7175, "load_act": null, "solar_fcst": 0.0, "solar_act": null, "wind_fcst": 19755.4, "wind_act": null, "net_load_fcst": 37994.3175, "net_load_act": null, "hsl_outage": 4373.0}, {"date": "2026-07-25", "he": 6, "load_fcst": 57007.3107, "load_act": null, "solar_fcst": 0.0, "solar_act": null, "wind_fcst": 18687.5, "wind_act": null, "net_load_fcst": 38319.8107, "net_load_act": null, "hsl_outage": 4373.0}, {"date": "2026-07-25", "he": 7, "load_fcst": 56430.6003, "load_act": null, "solar_fcst": 93.0, "solar_act": null, "wind_fcst": 17619.5, "wind_act": null, "net_load_fcst": 38718.1003, "net_load_act": null, "hsl_outage": 4373.0}, {"date": "2026-07-25", "he": 8, "load_fcst": 56944.9468, "load_act": null, "solar_fcst": 5093.1, "solar_act": null, "wind_fcst": 16032.9, "wind_act": null, "net_load_fcst": 35818.9468, "net_load_act": null, "hsl_outage": 4373.0}, {"date": "2026-07-25", "he": 9, "load_fcst": 60179.1792, "load_act": null, "solar_fcst": 19232.0, "solar_act": null, "wind_fcst": 15110.3, "wind_act": null, "net_load_fcst": 25836.8792, "net_load_act": null, "hsl_outage": 4373.0}, {"date": "2026-07-25", "he": 10, "load_fcst": 64808.265, "load_act": null, "solar_fcst": 27789.8, "solar_act": null, "wind_fcst": 14191.7, "wind_act": null, "net_load_fcst": 22826.764999999996, "net_load_act": null, "hsl_outage": 4373.0}, {"date": "2026-07-25", "he": 11, "load_fcst": 69510.751, "load_act": null, "solar_fcst": 30967.3, "solar_act": null, "wind_fcst": 13147.9, "wind_act": null, "net_load_fcst": 25395.551, "net_load_act": null, "hsl_outage": 4373.0}, {"date": "2026-07-25", "he": 12, "load_fcst": 74112.8606, "load_act": null, "solar_fcst": 32615.9, "solar_act": null, "wind_fcst": 11962.6, "wind_act": null, "net_load_fcst": 29534.3606, "net_load_act": null, "hsl_outage": 4373.0}, {"date": "2026-07-25", "he": 13, "load_fcst": 78116.437, "load_act": null, "solar_fcst": 33137.6, "solar_act": null, "wind_fcst": 10784.2, "wind_act": null, "net_load_fcst": 34194.637, "net_load_act": null, "hsl_outage": 4373.0}, {"date": "2026-07-25", "he": 14, "load_fcst": 81210.0227, "load_act": null, "solar_fcst": 33266.5, "solar_act": null, "wind_fcst": 9776.9, "wind_act": null, "net_load_fcst": 38166.6227, "net_load_act": null, "hsl_outage": 4373.0}, {"date": "2026-07-25", "he": 15, "load_fcst": 83081.2082, "load_act": null, "solar_fcst": 32962.8, "solar_act": null, "wind_fcst": 11038.8, "wind_act": null, "net_load_fcst": 39079.60819999999, "net_load_act": null, "hsl_outage": 4373.0}, {"date": "2026-07-25", "he": 16, "load_fcst": 84114.9556, "load_act": null, "solar_fcst": 32283.5, "solar_act": null, "wind_fcst": 12299.6, "wind_act": null, "net_load_fcst": 39531.8556, "net_load_act": null, "hsl_outage": 4373.0}, {"date": "2026-07-25", "he": 17, "load_fcst": 84407.6375, "load_act": null, "solar_fcst": 32499.0, "solar_act": null, "wind_fcst": 13677.8, "wind_act": null, "net_load_fcst": 38230.837499999994, "net_load_act": null, "hsl_outage": 4373.0}, {"date": "2026-07-25", "he": 18, "load_fcst": 84201.3254, "load_act": null, "solar_fcst": 30723.9, "solar_act": null, "wind_fcst": 15358.5, "wind_act": null, "net_load_fcst": 38118.9254, "net_load_act": null, "hsl_outage": 4373.0}, {"date": "2026-07-25", "he": 19, "load_fcst": 83312.385, "load_act": null, "solar_fcst": 25065.6, "solar_act": null, "wind_fcst": 15022.6, "wind_act": null, "net_load_fcst": 43224.185, "net_load_act": null, "hsl_outage": 4373.0}, {"date": "2026-07-25", "he": 20, "load_fcst": 81432.6096, "load_act": null, "solar_fcst": 11104.1, "solar_act": null, "wind_fcst": 16604.8, "wind_act": null, "net_load_fcst": 53723.70959999999, "net_load_act": null, "hsl_outage": 4373.0}, {"date": "2026-07-25", "he": 21, "load_fcst": 78645.687, "load_act": null, "solar_fcst": 932.0, "solar_act": null, "wind_fcst": 18248.4, "wind_act": null, "net_load_fcst": 59465.287000000004, "net_load_act": null, "hsl_outage": 4373.0}, {"date": "2026-07-25", "he": 22, "load_fcst": 76641.0051, "load_act": null, "solar_fcst": 0.0, "solar_act": null, "wind_fcst": 19891.4, "wind_act": null, "net_load_fcst": 56749.60509999999, "net_load_act": null, "hsl_outage": 4373.0}, {"date": "2026-07-25", "he": 23, "load_fcst": 73394.7755, "load_act": null, "solar_fcst": 0.0, "solar_act": null, "wind_fcst": 21187.0, "wind_act": null, "net_load_fcst": 52207.7755, "net_load_act": null, "hsl_outage": 4373.0}, {"date": "2026-07-25", "he": 24, "load_fcst": 69758.0671, "load_act": null, "solar_fcst": 0.0, "solar_act": null, "wind_fcst": 22037.3, "wind_act": null, "net_load_fcst": 47720.7671, "net_load_act": null, "hsl_outage": 4298.0}, {"date": "2026-07-26", "he": 1, "load_fcst": 66059.9248, "load_act": null, "solar_fcst": 0.0, "solar_act": null, "wind_fcst": 23086.2, "wind_act": null, "net_load_fcst": 42973.724799999996, "net_load_act": null, "hsl_outage": 4298.0}, {"date": "2026-07-26", "he": 2, "load_fcst": 62690.0407, "load_act": null, "solar_fcst": 0.0, "solar_act": null, "wind_fcst": 22322.8, "wind_act": null, "net_load_fcst": 40367.240699999995, "net_load_act": null, "hsl_outage": 4298.0}, {"date": "2026-07-26", "he": 3, "load_fcst": 60139.2, "load_act": null, "solar_fcst": 0.0, "solar_act": null, "wind_fcst": 21584.4, "wind_act": null, "net_load_fcst": 38554.799999999996, "net_load_act": null, "hsl_outage": 4298.0}, {"date": "2026-07-26", "he": 4, "load_fcst": 58233.9418, "load_act": null, "solar_fcst": 0.0, "solar_act": null, "wind_fcst": 20838.6, "wind_act": null, "net_load_fcst": 37395.3418, "net_load_act": null, "hsl_outage": 4298.0}, {"date": "2026-07-26", "he": 5, "load_fcst": 56881.056899999996, "load_act": null, "solar_fcst": 0.0, "solar_act": null, "wind_fcst": 20012.5, "wind_act": null, "net_load_fcst": 36868.556899999996, "net_load_act": null, "hsl_outage": 4298.0}, {"date": "2026-07-26", "he": 6, "load_fcst": 55974.4127, "load_act": null, "solar_fcst": 0.0, "solar_act": null, "wind_fcst": 19098.4, "wind_act": null, "net_load_fcst": 36876.0127, "net_load_act": null, "hsl_outage": 4298.0}, {"date": "2026-07-26", "he": 7, "load_fcst": 55115.5911, "load_act": null, "solar_fcst": 74.6, "solar_act": null, "wind_fcst": 18183.2, "wind_act": null, "net_load_fcst": 36857.7911, "net_load_act": null, "hsl_outage": 4298.0}, {"date": "2026-07-26", "he": 8, "load_fcst": 55387.5965, "load_act": null, "solar_fcst": 4405.5, "solar_act": null, "wind_fcst": 14911.1, "wind_act": null, "net_load_fcst": 36070.9965, "net_load_act": null, "hsl_outage": 4298.0}, {"date": "2026-07-26", "he": 9, "load_fcst": 58640.8366, "load_act": null, "solar_fcst": 16939.9, "solar_act": null, "wind_fcst": 13942.3, "wind_act": null, "net_load_fcst": 27758.6366, "net_load_act": null, "hsl_outage": 4298.0}, {"date": "2026-07-26", "he": 10, "load_fcst": 63435.2491, "load_act": null, "solar_fcst": 25117.0, "solar_act": null, "wind_fcst": 12974.5, "wind_act": null, "net_load_fcst": 25343.7491, "net_load_act": null, "hsl_outage": 4298.0}, {"date": "2026-07-26", "he": 11, "load_fcst": 68266.6861, "load_act": null, "solar_fcst": 28456.4, "solar_act": null, "wind_fcst": 11993.7, "wind_act": null, "net_load_fcst": 27816.586100000004, "net_load_act": null, "hsl_outage": 4298.0}, {"date": "2026-07-26", "he": 12, "load_fcst": 73008.5238, "load_act": null, "solar_fcst": 30238.0, "solar_act": null, "wind_fcst": 10999.8, "wind_act": null, "net_load_fcst": 31770.723799999996, "net_load_act": null, "hsl_outage": 4298.0}, {"date": "2026-07-26", "he": 13, "load_fcst": 77247.06360000001, "load_act": null, "solar_fcst": 31293.2, "solar_act": null, "wind_fcst": 10006.6, "wind_act": null, "net_load_fcst": 35947.26360000001, "net_load_act": null, "hsl_outage": 4298.0}, {"date": "2026-07-26", "he": 14, "load_fcst": 80658.7799, "load_act": null, "solar_fcst": 32726.9, "solar_act": null, "wind_fcst": 9954.0, "wind_act": null, "net_load_fcst": 37977.87989999999, "net_load_act": null, "hsl_outage": 4298.0}, {"date": "2026-07-26", "he": 15, "load_fcst": 82748.4399, "load_act": null, "solar_fcst": 32427.3, "solar_act": null, "wind_fcst": 10815.3, "wind_act": null, "net_load_fcst": 39505.83989999999, "net_load_act": null, "hsl_outage": 4298.0}, {"date": "2026-07-26", "he": 16, "load_fcst": 84100.0291, "load_act": null, "solar_fcst": 31753.6, "solar_act": null, "wind_fcst": 11677.7, "wind_act": null, "net_load_fcst": 40668.7291, "net_load_act": null, "hsl_outage": 4298.0}, {"date": "2026-07-26", "he": 17, "load_fcst": 84619.0757, "load_act": null, "solar_fcst": 31637.1, "solar_act": null, "wind_fcst": 12656.8, "wind_act": null, "net_load_fcst": 40325.17570000001, "net_load_act": null, "hsl_outage": 4298.0}, {"date": "2026-07-26", "he": 18, "load_fcst": 84855.5371, "load_act": null, "solar_fcst": 29697.7, "solar_act": null, "wind_fcst": 13809.0, "wind_act": null, "net_load_fcst": 41348.837100000004, "net_load_act": null, "hsl_outage": 4298.0}, {"date": "2026-07-26", "he": 19, "load_fcst": 84209.7169, "load_act": null, "solar_fcst": 24014.4, "solar_act": null, "wind_fcst": 16351.1, "wind_act": null, "net_load_fcst": 43844.2169, "net_load_act": null, "hsl_outage": 4298.0}, {"date": "2026-07-26", "he": 20, "load_fcst": 82622.64199999999, "load_act": null, "solar_fcst": 10423.3, "solar_act": null, "wind_fcst": 17648.2, "wind_act": null, "net_load_fcst": 54551.14199999999, "net_load_act": null, "hsl_outage": 4298.0}, {"date": "2026-07-26", "he": 21, "load_fcst": 79954.6886, "load_act": null, "solar_fcst": 814.1, "solar_act": null, "wind_fcst": 19070.9, "wind_act": null, "net_load_fcst": 60069.68859999999, "net_load_act": null, "hsl_outage": 4298.0}, {"date": "2026-07-26", "he": 22, "load_fcst": 77909.6284, "load_act": null, "solar_fcst": 0.0, "solar_act": null, "wind_fcst": 20486.0, "wind_act": null, "net_load_fcst": 57423.6284, "net_load_act": null, "hsl_outage": 4298.0}, {"date": "2026-07-26", "he": 23, "load_fcst": 74268.568, "load_act": null, "solar_fcst": 0.0, "solar_act": null, "wind_fcst": 21588.8, "wind_act": null, "net_load_fcst": 52679.768, "net_load_act": null, "hsl_outage": 4298.0}, {"date": "2026-07-26", "he": 24, "load_fcst": 69990.7478, "load_act": null, "solar_fcst": 0.0, "solar_act": null, "wind_fcst": 22346.9, "wind_act": null, "net_load_fcst": 47643.847799999996, "net_load_act": null, "hsl_outage": 4219.0}, {"date": "2026-07-27", "he": 1, "load_fcst": 65960.1479, "load_act": null, "solar_fcst": 0.0, "solar_act": null, "wind_fcst": 23131.3, "wind_act": null, "net_load_fcst": 42828.84789999999, "net_load_act": null, "hsl_outage": 4219.0}, {"date": "2026-07-27", "he": 2, "load_fcst": 62663.4116, "load_act": null, "solar_fcst": 0.0, "solar_act": null, "wind_fcst": 23429.1, "wind_act": null, "net_load_fcst": 39234.3116, "net_load_act": null, "hsl_outage": 4219.0}, {"date": "2026-07-27", "he": 3, "load_fcst": 60256.5146, "load_act": null, "solar_fcst": 0.0, "solar_act": null, "wind_fcst": 22398.4, "wind_act": null, "net_load_fcst": 37858.1146, "net_load_act": null, "hsl_outage": 4219.0}, {"date": "2026-07-27", "he": 4, "load_fcst": 58603.8345, "load_act": null, "solar_fcst": 0.0, "solar_act": null, "wind_fcst": 21365.8, "wind_act": null, "net_load_fcst": 37238.034499999994, "net_load_act": null, "hsl_outage": 4219.0}, {"date": "2026-07-27", "he": 5, "load_fcst": 57909.6778, "load_act": null, "solar_fcst": 0.0, "solar_act": null, "wind_fcst": 20241.6, "wind_act": null, "net_load_fcst": 37668.0778, "net_load_act": null, "hsl_outage": 4219.0}, {"date": "2026-07-27", "he": 6, "load_fcst": 58302.935, "load_act": null, "solar_fcst": 0.0, "solar_act": null, "wind_fcst": 19008.3, "wind_act": null, "net_load_fcst": 39294.634999999995, "net_load_act": null, "hsl_outage": 4219.0}, {"date": "2026-07-27", "he": 7, "load_fcst": 58910.2302, "load_act": null, "solar_fcst": 79.7, "solar_act": null, "wind_fcst": 17524.4, "wind_act": null, "net_load_fcst": 41306.1302, "net_load_act": null, "hsl_outage": 4219.0}, {"date": "2026-07-27", "he": 8, "load_fcst": 59786.4991, "load_act": null, "solar_fcst": 4887.5, "solar_act": null, "wind_fcst": 16760.9, "wind_act": null, "net_load_fcst": 38138.0991, "net_load_act": null, "hsl_outage": 4219.0}, {"date": "2026-07-27", "he": 9, "load_fcst": 62806.3987, "load_act": null, "solar_fcst": 18888.5, "solar_act": null, "wind_fcst": 15098.4, "wind_act": null, "net_load_fcst": 28819.498699999996, "net_load_act": null, "hsl_outage": 4219.0}, {"date": "2026-07-27", "he": 10, "load_fcst": 67148.62879999999, "load_act": null, "solar_fcst": 27634.8, "solar_act": null, "wind_fcst": 13434.4, "wind_act": null, "net_load_fcst": 26079.428799999987, "net_load_act": null, "hsl_outage": 4229.0}, {"date": "2026-07-27", "he": 11, "load_fcst": 71999.9377, "load_act": null, "solar_fcst": 30837.2, "solar_act": null, "wind_fcst": 11658.6, "wind_act": null, "net_load_fcst": 29504.1377, "net_load_act": null, "hsl_outage": 4229.0}, {"date": "2026-07-27", "he": 12, "load_fcst": 76633.4143, "load_act": null, "solar_fcst": 32627.4, "solar_act": null, "wind_fcst": 9851.4, "wind_act": null, "net_load_fcst": 34154.6143, "net_load_act": null, "hsl_outage": 4229.0}, {"date": "2026-07-27", "he": 13, "load_fcst": 80916.9769, "load_act": null, "solar_fcst": 33338.4, "solar_act": null, "wind_fcst": 8049.7, "wind_act": null, "net_load_fcst": 39528.876899999996, "net_load_act": null, "hsl_outage": 4219.0}, {"date": "2026-07-27", "he": 14, "load_fcst": 84479.806, "load_act": null, "solar_fcst": 34245.7, "solar_act": null, "wind_fcst": 9438.9, "wind_act": null, "net_load_fcst": 40795.206, "net_load_act": null, "hsl_outage": 4219.0}, {"date": "2026-07-27", "he": 15, "load_fcst": 86289.2002, "load_act": null, "solar_fcst": 33881.5, "solar_act": null, "wind_fcst": 10589.9, "wind_act": null, "net_load_fcst": 41817.800200000005, "net_load_act": null, "hsl_outage": 4219.0}, {"date": "2026-07-27", "he": 16, "load_fcst": 87110.5918, "load_act": null, "solar_fcst": 33259.1, "solar_act": null, "wind_fcst": 11742.8, "wind_act": null, "net_load_fcst": 42108.6918, "net_load_act": null, "hsl_outage": 4219.0}, {"date": "2026-07-27", "he": 17, "load_fcst": 87507.7053, "load_act": null, "solar_fcst": 33360.2, "solar_act": null, "wind_fcst": 13069.6, "wind_act": null, "net_load_fcst": 41077.905300000006, "net_load_act": null, "hsl_outage": 4219.0}, {"date": "2026-07-27", "he": 18, "load_fcst": 87732.4814, "load_act": null, "solar_fcst": 31392.2, "solar_act": null, "wind_fcst": 14620.6, "wind_act": null, "net_load_fcst": 41719.68140000001, "net_load_act": null, "hsl_outage": 4219.0}, {"date": "2026-07-27", "he": 19, "load_fcst": 87571.2498, "load_act": null, "solar_fcst": 25498.0, "solar_act": null, "wind_fcst": 16004.0, "wind_act": null, "net_load_fcst": 46069.249800000005, "net_load_act": null, "hsl_outage": 4209.0}, {"date": "2026-07-27", "he": 20, "load_fcst": 86231.14140000001, "load_act": null, "solar_fcst": 10022.7, "solar_act": null, "wind_fcst": 19016.3, "wind_act": null, "net_load_fcst": 57192.14140000001, "net_load_act": null, "hsl_outage": 4209.0}, {"date": "2026-07-27", "he": 21, "load_fcst": 83378.927, "load_act": null, "solar_fcst": 759.3, "solar_act": null, "wind_fcst": 20265.8, "wind_act": null, "net_load_fcst": 62353.82699999999, "net_load_act": null, "hsl_outage": 4398.0}, {"date": "2026-07-27", "he": 22, "load_fcst": 80910.6446, "load_act": null, "solar_fcst": 0.0, "solar_act": null, "wind_fcst": 21495.4, "wind_act": null, "net_load_fcst": 59415.2446, "net_load_act": null, "hsl_outage": 4398.0}, {"date": "2026-07-27", "he": 23, "load_fcst": 76754.1635, "load_act": null, "solar_fcst": 0.0, "solar_act": null, "wind_fcst": 22405.3, "wind_act": null, "net_load_fcst": 54348.86349999999, "net_load_act": null, "hsl_outage": 4398.0}, {"date": "2026-07-27", "he": 24, "load_fcst": 72185.6269, "load_act": null, "solar_fcst": 0.0, "solar_act": null, "wind_fcst": 22898.0, "wind_act": null, "net_load_fcst": 49287.6269, "net_load_act": null, "hsl_outage": 4362.0}, {"date": "2026-07-28", "he": 1, "load_fcst": 67882.7847, "load_act": null, "solar_fcst": 0.0, "solar_act": null, "wind_fcst": 23420.8, "wind_act": null, "net_load_fcst": 44461.9847, "net_load_act": null, "hsl_outage": 4049.0}, {"date": "2026-07-28", "he": 2, "load_fcst": 64330.2321, "load_act": null, "solar_fcst": 0.0, "solar_act": null, "wind_fcst": 24378.9, "wind_act": null, "net_load_fcst": 39951.3321, "net_load_act": null, "hsl_outage": 4049.0}, {"date": "2026-07-28", "he": 3, "load_fcst": 61623.5038, "load_act": null, "solar_fcst": 0.0, "solar_act": null, "wind_fcst": 23687.7, "wind_act": null, "net_load_fcst": 37935.803799999994, "net_load_act": null, "hsl_outage": 4049.0}, {"date": "2026-07-28", "he": 4, "load_fcst": 59766.0348, "load_act": null, "solar_fcst": 0.0, "solar_act": null, "wind_fcst": 23005.5, "wind_act": null, "net_load_fcst": 36760.5348, "net_load_act": null, "hsl_outage": 4049.0}, {"date": "2026-07-28", "he": 5, "load_fcst": 58868.6007, "load_act": null, "solar_fcst": 0.0, "solar_act": null, "wind_fcst": 22231.2, "wind_act": null, "net_load_fcst": 36637.4007, "net_load_act": null, "hsl_outage": 4049.0}, {"date": "2026-07-28", "he": 6, "load_fcst": 59216.4076, "load_act": null, "solar_fcst": 0.0, "solar_act": null, "wind_fcst": 21353.7, "wind_act": null, "net_load_fcst": 37862.707599999994, "net_load_act": null, "hsl_outage": 4049.0}, {"date": "2026-07-28", "he": 7, "load_fcst": 59798.074, "load_act": null, "solar_fcst": 72.7, "solar_act": null, "wind_fcst": 20250.0, "wind_act": null, "net_load_fcst": 39475.374, "net_load_act": null, "hsl_outage": 4094.0}, {"date": "2026-07-28", "he": 8, "load_fcst": 60589.145300000004, "load_act": null, "solar_fcst": 4773.7, "solar_act": null, "wind_fcst": 18557.9, "wind_act": null, "net_load_fcst": 37257.545300000005, "net_load_act": null, "hsl_outage": 4094.0}, {"date": "2026-07-28", "he": 9, "load_fcst": 63403.5767, "load_act": null, "solar_fcst": 18751.2, "solar_act": null, "wind_fcst": 17396.2, "wind_act": null, "net_load_fcst": 27256.176699999993, "net_load_act": null, "hsl_outage": 4407.0}, {"date": "2026-07-28", "he": 10, "load_fcst": 67791.5267, "load_act": null, "solar_fcst": 27631.1, "solar_act": null, "wind_fcst": 16232.5, "wind_act": null, "net_load_fcst": 23927.926700000004, "net_load_act": null, "hsl_outage": 4417.0}, {"date": "2026-07-28", "he": 11, "load_fcst": 72620.7663, "load_act": null, "solar_fcst": 30991.1, "solar_act": null, "wind_fcst": 14944.9, "wind_act": null, "net_load_fcst": 26684.766300000003, "net_load_act": null, "hsl_outage": 4197.0}, {"date": "2026-07-28", "he": 12, "load_fcst": 77323.0163, "load_act": null, "solar_fcst": 32835.5, "solar_act": null, "wind_fcst": 13530.8, "wind_act": null, "net_load_fcst": 30956.716300000004, "net_load_act": null, "hsl_outage": 4197.0}, {"date": "2026-07-28", "he": 13, "load_fcst": 81770.6159, "load_act": null, "solar_fcst": 33554.7, "solar_act": null, "wind_fcst": 12114.1, "wind_act": null, "net_load_fcst": 36101.81590000001, "net_load_act": null, "hsl_outage": 4142.0}, {"date": "2026-07-28", "he": 14, "load_fcst": 85478.3959, "load_act": null, "solar_fcst": 34185.8, "solar_act": null, "wind_fcst": 12501.8, "wind_act": null, "net_load_fcst": 38790.7959, "net_load_act": null, "hsl_outage": 4142.0}, {"date": "2026-07-28", "he": 15, "load_fcst": 87315.8516, "load_act": null, "solar_fcst": 33937.7, "solar_act": null, "wind_fcst": 13636.4, "wind_act": null, "net_load_fcst": 39741.751599999996, "net_load_act": null, "hsl_outage": 4142.0}, {"date": "2026-07-28", "he": 16, "load_fcst": 88174.3817, "load_act": null, "solar_fcst": 33251.7, "solar_act": null, "wind_fcst": 14706.8, "wind_act": null, "net_load_fcst": 40215.8817, "net_load_act": null, "hsl_outage": 4142.0}, {"date": "2026-07-28", "he": 17, "load_fcst": 88522.0689, "load_act": null, "solar_fcst": 33338.1, "solar_act": null, "wind_fcst": 15861.9, "wind_act": null, "net_load_fcst": 39322.0689, "net_load_act": null, "hsl_outage": 4142.0}, {"date": "2026-07-28", "he": 18, "load_fcst": 88794.9904, "load_act": null, "solar_fcst": 31490.9, "solar_act": null, "wind_fcst": 17042.0, "wind_act": null, "net_load_fcst": 40262.090399999994, "net_load_act": null, "hsl_outage": 4142.0}, {"date": "2026-07-28", "he": 19, "load_fcst": 88651.5542, "load_act": null, "solar_fcst": 25645.5, "solar_act": null, "wind_fcst": 17120.9, "wind_act": null, "net_load_fcst": 45885.1542, "net_load_act": null, "hsl_outage": 4142.0}, {"date": "2026-07-28", "he": 20, "load_fcst": 87385.2737, "load_act": null, "solar_fcst": 10822.7, "solar_act": null, "wind_fcst": 18846.9, "wind_act": null, "net_load_fcst": 57715.67370000001, "net_load_act": null, "hsl_outage": 4142.0}, {"date": "2026-07-28", "he": 21, "load_fcst": 84490.7129, "load_act": null, "solar_fcst": 790.7, "solar_act": null, "wind_fcst": 19666.9, "wind_act": null, "net_load_fcst": 64033.1129, "net_load_act": null, "hsl_outage": 4142.0}, {"date": "2026-07-28", "he": 22, "load_fcst": 82071.0154, "load_act": null, "solar_fcst": 0.0, "solar_act": null, "wind_fcst": 20486.7, "wind_act": null, "net_load_fcst": 61584.31540000001, "net_load_act": null, "hsl_outage": 4142.0}, {"date": "2026-07-28", "he": 23, "load_fcst": 77891.2432, "load_act": null, "solar_fcst": 0.0, "solar_act": null, "wind_fcst": 21146.8, "wind_act": null, "net_load_fcst": 56744.443199999994, "net_load_act": null, "hsl_outage": 4142.0}, {"date": "2026-07-28", "he": 24, "load_fcst": 73343.9922, "load_act": null, "solar_fcst": 0.0, "solar_act": null, "wind_fcst": 21618.9, "wind_act": null, "net_load_fcst": 51725.09219999999, "net_load_act": null, "hsl_outage": 4090.0}, {"date": "2026-07-29", "he": 1, "load_fcst": 68898.9959, "load_act": null, "solar_fcst": 0.0, "solar_act": null, "wind_fcst": 22103.4, "wind_act": null, "net_load_fcst": 46795.59589999999, "net_load_act": null, "hsl_outage": 4090.0}, {"date": "2026-07-29", "he": 2, "load_fcst": 65294.653600000005, "load_act": null, "solar_fcst": 0.0, "solar_act": null, "wind_fcst": 22401.2, "wind_act": null, "net_load_fcst": 42893.45360000001, "net_load_act": null, "hsl_outage": 4090.0}, {"date": "2026-07-29", "he": 3, "load_fcst": 62551.716700000004, "load_act": null, "solar_fcst": 0.0, "solar_act": null, "wind_fcst": 21484.1, "wind_act": null, "net_load_fcst": 41067.616700000006, "net_load_act": null, "hsl_outage": 4090.0}, {"date": "2026-07-29", "he": 4, "load_fcst": 60617.1402, "load_act": null, "solar_fcst": 0.0, "solar_act": null, "wind_fcst": 20559.2, "wind_act": null, "net_load_fcst": 40057.9402, "net_load_act": null, "hsl_outage": 4090.0}, {"date": "2026-07-29", "he": 5, "load_fcst": 59646.4717, "load_act": null, "solar_fcst": 0.0, "solar_act": null, "wind_fcst": 19534.5, "wind_act": null, "net_load_fcst": 40111.9717, "net_load_act": null, "hsl_outage": 4090.0}, {"date": "2026-07-29", "he": 6, "load_fcst": 59875.4381, "load_act": null, "solar_fcst": 0.0, "solar_act": null, "wind_fcst": 18434.4, "wind_act": null, "net_load_fcst": 41441.0381, "net_load_act": null, "hsl_outage": 4090.0}, {"date": "2026-07-29", "he": 7, "load_fcst": 60385.2055, "load_act": null, "solar_fcst": 71.9, "solar_act": null, "wind_fcst": 17915.0, "wind_act": null, "net_load_fcst": 42398.305499999995, "net_load_act": null, "hsl_outage": 4090.0}, {"date": "2026-07-29", "he": 8, "load_fcst": 61086.411, "load_act": null, "solar_fcst": 5004.2, "solar_act": null, "wind_fcst": 16862.7, "wind_act": null, "net_load_fcst": 39219.511, "net_load_act": null, "hsl_outage": 4090.0}, {"date": "2026-07-29", "he": 9, "load_fcst": 63839.7595, "load_act": null, "solar_fcst": 19812.2, "solar_act": null, "wind_fcst": 15723.7, "wind_act": null, "net_load_fcst": 28303.859500000002, "net_load_act": null, "hsl_outage": 4090.0}, {"date": "2026-07-29", "he": 10, "load_fcst": 68391.9111, "load_act": null, "solar_fcst": null, "solar_act": null, "wind_fcst": null, "wind_act": null, "net_load_fcst": null, "net_load_act": null, "hsl_outage": 4090.0}, {"date": "2026-07-29", "he": 11, "load_fcst": 73394.5515, "load_act": null, "solar_fcst": null, "solar_act": null, "wind_fcst": null, "wind_act": null, "net_load_fcst": null, "net_load_act": null, "hsl_outage": 4090.0}, {"date": "2026-07-29", "he": 12, "load_fcst": 78214.8967, "load_act": null, "solar_fcst": null, "solar_act": null, "wind_fcst": null, "wind_act": null, "net_load_fcst": null, "net_load_act": null, "hsl_outage": 4090.0}, {"date": "2026-07-29", "he": 13, "load_fcst": 82722.0883, "load_act": null, "solar_fcst": null, "solar_act": null, "wind_fcst": null, "wind_act": null, "net_load_fcst": null, "net_load_act": null, "hsl_outage": 4090.0}, {"date": "2026-07-29", "he": 14, "load_fcst": 86383.0056, "load_act": null, "solar_fcst": null, "solar_act": null, "wind_fcst": null, "wind_act": null, "net_load_fcst": null, "net_load_act": null, "hsl_outage": 4090.0}, {"date": "2026-07-29", "he": 15, "load_fcst": 87993.658, "load_act": null, "solar_fcst": null, "solar_act": null, "wind_fcst": null, "wind_act": null, "net_load_fcst": null, "net_load_act": null, "hsl_outage": 4090.0}, {"date": "2026-07-29", "he": 16, "load_fcst": 88706.3059, "load_act": null, "solar_fcst": null, "solar_act": null, "wind_fcst": null, "wind_act": null, "net_load_fcst": null, "net_load_act": null, "hsl_outage": 4090.0}, {"date": "2026-07-29", "he": 17, "load_fcst": 88850.6379, "load_act": null, "solar_fcst": null, "solar_act": null, "wind_fcst": null, "wind_act": null, "net_load_fcst": null, "net_load_act": null, "hsl_outage": 4090.0}, {"date": "2026-07-29", "he": 18, "load_fcst": 88967.4389, "load_act": null, "solar_fcst": null, "solar_act": null, "wind_fcst": null, "wind_act": null, "net_load_fcst": null, "net_load_act": null, "hsl_outage": 4090.0}, {"date": "2026-07-29", "he": 19, "load_fcst": 88737.7012, "load_act": null, "solar_fcst": null, "solar_act": null, "wind_fcst": null, "wind_act": null, "net_load_fcst": null, "net_load_act": null, "hsl_outage": 4090.0}, {"date": "2026-07-29", "he": 20, "load_fcst": 87347.5412, "load_act": null, "solar_fcst": null, "solar_act": null, "wind_fcst": null, "wind_act": null, "net_load_fcst": null, "net_load_act": null, "hsl_outage": 4090.0}, {"date": "2026-07-29", "he": 21, "load_fcst": 84523.7982, "load_act": null, "solar_fcst": null, "solar_act": null, "wind_fcst": null, "wind_act": null, "net_load_fcst": null, "net_load_act": null, "hsl_outage": 4090.0}, {"date": "2026-07-29", "he": 22, "load_fcst": 82222.3987, "load_act": null, "solar_fcst": null, "solar_act": null, "wind_fcst": null, "wind_act": null, "net_load_fcst": null, "net_load_act": null, "hsl_outage": 4090.0}, {"date": "2026-07-29", "he": 23, "load_fcst": 78053.5794, "load_act": null, "solar_fcst": null, "solar_act": null, "wind_fcst": null, "wind_act": null, "net_load_fcst": null, "net_load_act": null, "hsl_outage": 4090.0}, {"date": "2026-07-29", "he": 24, "load_fcst": 73532.2545, "load_act": null, "solar_fcst": null, "solar_act": null, "wind_fcst": null, "wind_act": null, "net_load_fcst": null, "net_load_act": null, "hsl_outage": null}]}