{"generated_at": "2026-07-20 08:09 CDT", "now_date": "2026-07-20", "now_he": 9, "points": [{"date": "2026-07-19", "he": 1, "load_fcst": 62300.7496, "load_act": 62249.14, "solar_fcst": 0.0, "solar_act": 0.14, "wind_fcst": 19992.2, "wind_act": 11653.96, "net_load_fcst": 42308.5496, "net_load_act": 50595.04, "hsl_outage": 7978.0}, {"date": "2026-07-19", "he": 2, "load_fcst": 59458.7892, "load_act": 59502.55, "solar_fcst": 0.0, "solar_act": 0.31, "wind_fcst": 19267.3, "wind_act": 9712.91, "net_load_fcst": 40191.489199999996, "net_load_act": 49789.33, "hsl_outage": 8045.0}, {"date": "2026-07-19", "he": 3, "load_fcst": 57238.6109, "load_act": 57496.35, "solar_fcst": 0.0, "solar_act": 0.23, "wind_fcst": 17948.3, "wind_act": 8789.21, "net_load_fcst": 39290.3109, "net_load_act": 48706.909999999996, "hsl_outage": 8066.0}, {"date": "2026-07-19", "he": 4, "load_fcst": 55865.8297, "load_act": 55956.07, "solar_fcst": 0.0, "solar_act": 0.21, "wind_fcst": 16628.5, "wind_act": 8699.09, "net_load_fcst": 39237.3297, "net_load_act": 47256.770000000004, "hsl_outage": 8062.0}, {"date": "2026-07-19", "he": 5, "load_fcst": 54718.5203, "load_act": 54960.51, "solar_fcst": 0.0, "solar_act": 0.22, "wind_fcst": 15337.8, "wind_act": 8821.43, "net_load_fcst": 39380.7203, "net_load_act": 46138.86, "hsl_outage": 8512.0}, {"date": "2026-07-19", "he": 6, "load_fcst": 54000.409700000004, "load_act": 54355.65, "solar_fcst": 0.0, "solar_act": 0.33, "wind_fcst": 14080.9, "wind_act": 8474.05, "net_load_fcst": 39919.5097, "net_load_act": 45881.270000000004, "hsl_outage": 8497.0}, {"date": "2026-07-19", "he": 7, "load_fcst": 53400.7498, "load_act": 53787.67, "solar_fcst": 143.6, "solar_act": 80.68, "wind_fcst": 13860.3, "wind_act": 8115.68, "net_load_fcst": 39396.849799999996, "net_load_act": 45591.31, "hsl_outage": 8490.0}, {"date": "2026-07-19", "he": 8, "load_fcst": 54046.7994, "load_act": 53929.85, "solar_fcst": 5606.0, "solar_act": 4463.64, "wind_fcst": 13370.0, "wind_act": 8159.36, "net_load_fcst": 35070.7994, "net_load_act": 41306.85, "hsl_outage": 8490.0}, {"date": "2026-07-19", "he": 9, "load_fcst": 57285.8407, "load_act": 56760.22, "solar_fcst": 18954.3, "solar_act": 16135.48, "wind_fcst": 12762.0, "wind_act": 7072.53, "net_load_fcst": 25569.540699999998, "net_load_act": 33552.21000000001, "hsl_outage": 8490.0}, {"date": "2026-07-19", "he": 10, "load_fcst": 60919.5803, "load_act": 60818.49, "solar_fcst": 26976.7, "solar_act": 24953.14, "wind_fcst": 12155.0, "wind_act": 8911.44, "net_load_fcst": 21787.880300000004, "net_load_act": 26953.909999999996, "hsl_outage": 7958.0}, {"date": "2026-07-19", "he": 11, "load_fcst": 64954.149900000004, "load_act": 65150.29, "solar_fcst": 30414.6, "solar_act": 29830.06, "wind_fcst": 11475.0, "wind_act": 9968.06, "net_load_fcst": 23064.549900000005, "net_load_act": 25352.17, "hsl_outage": 7958.0}, {"date": "2026-07-19", "he": 12, "load_fcst": 69654.3594, "load_act": 69685.87, "solar_fcst": 32366.6, "solar_act": 31781.32, "wind_fcst": 10711.5, "wind_act": 9239.99, "net_load_fcst": 26576.259400000003, "net_load_act": 28664.559999999998, "hsl_outage": 7958.0}, {"date": "2026-07-19", "he": 13, "load_fcst": 73748.8483, "load_act": 73774.82, "solar_fcst": 32747.3, "solar_act": 32224.06, "wind_fcst": 9014.8, "wind_act": 8768.8, "net_load_fcst": 31986.748299999996, "net_load_act": 32781.96000000001, "hsl_outage": 8071.0}, {"date": "2026-07-19", "he": 14, "load_fcst": 77234.9018, "load_act": 77388.68, "solar_fcst": 33062.3, "solar_act": 32538.79, "wind_fcst": 11416.4, "wind_act": 7986.31, "net_load_fcst": 32756.201800000003, "net_load_act": 36863.579999999994, "hsl_outage": 8071.0}, {"date": "2026-07-19", "he": 15, "load_fcst": 79953.9802, "load_act": 80250.55, "solar_fcst": 33085.3, "solar_act": 31973.47, "wind_fcst": 12409.4, "wind_act": 8215.47, "net_load_fcst": 34459.2802, "net_load_act": 40061.61, "hsl_outage": 8071.0}, {"date": "2026-07-19", "he": 16, "load_fcst": 82267.169, "load_act": 81966.28, "solar_fcst": 32541.9, "solar_act": 30930.24, "wind_fcst": 13403.3, "wind_act": 8759.98, "net_load_fcst": 36321.969, "net_load_act": 42276.06, "hsl_outage": 7901.0}, {"date": "2026-07-19", "he": 17, "load_fcst": 83059.4606, "load_act": 82617.49, "solar_fcst": 31746.9, "solar_act": 28623.23, "wind_fcst": 14315.0, "wind_act": 10763.51, "net_load_fcst": 36997.560600000004, "net_load_act": 43230.75000000001, "hsl_outage": 7901.0}, {"date": "2026-07-19", "he": 18, "load_fcst": 82113.3608, "load_act": 82654.92, "solar_fcst": 30144.1, "solar_act": 26372.14, "wind_fcst": 15129.1, "wind_act": 10711.72, "net_load_fcst": 36840.1608, "net_load_act": 45571.06, "hsl_outage": 7901.0}, {"date": "2026-07-19", "he": 19, "load_fcst": 80597.6401, "load_act": 81657.38, "solar_fcst": 25309.8, "solar_act": 20412.91, "wind_fcst": 17695.5, "wind_act": 11475.11, "net_load_fcst": 37592.3401, "net_load_act": 49769.36, "hsl_outage": 7783.0}, {"date": "2026-07-19", "he": 20, "load_fcst": 78410.1408, "load_act": 79722.59, "solar_fcst": 11447.4, "solar_act": 8580.7, "wind_fcst": 18266.7, "wind_act": 12301.57, "net_load_fcst": 48696.0408, "net_load_act": 58840.32, "hsl_outage": 7783.0}, {"date": "2026-07-19", "he": 21, "load_fcst": 76013.6605, "load_act": 76629.71, "solar_fcst": 1025.4, "solar_act": 628.63, "wind_fcst": 19301.4, "wind_act": 12797.08, "net_load_fcst": 55686.8605, "net_load_act": 63204.0, "hsl_outage": 7778.0}, {"date": "2026-07-19", "he": 22, "load_fcst": 74054.2792, "load_act": 74879.58, "solar_fcst": 0.0, "solar_act": 0.05, "wind_fcst": 19628.4, "wind_act": 13971.07, "net_load_fcst": 54425.8792, "net_load_act": 60908.46, "hsl_outage": 7778.0}, {"date": "2026-07-19", "he": 23, "load_fcst": 70403.8991, "load_act": 71296.61, "solar_fcst": 0.0, "solar_act": 0.07, "wind_fcst": 19873.1, "wind_act": 14082.52, "net_load_fcst": 50530.7991, "net_load_act": 57214.01999999999, "hsl_outage": 7778.0}, {"date": "2026-07-19", "he": 24, "load_fcst": 66214.9411, "load_act": 67075.14, "solar_fcst": 0.0, "solar_act": 0.09, "wind_fcst": 20024.0, "wind_act": 14764.22, "net_load_fcst": 46190.9411, "net_load_act": 52310.83, "hsl_outage": 6572.0}, {"date": "2026-07-20", "he": 1, "load_fcst": 62243.1604, "load_act": null, "solar_fcst": 0.0, "solar_act": 0.11, "wind_fcst": 20182.6, "wind_act": 14861.31, "net_load_fcst": 42060.5604, "net_load_act": null, "hsl_outage": 6722.0}, {"date": "2026-07-20", "he": 2, "load_fcst": 59091.6403, "load_act": null, "solar_fcst": 0.0, "solar_act": 0.11, "wind_fcst": 18863.6, "wind_act": 14576.34, "net_load_fcst": 40228.0403, "net_load_act": null, "hsl_outage": 6722.0}, {"date": "2026-07-20", "he": 3, "load_fcst": 56817.6497, "load_act": null, "solar_fcst": 0.0, "solar_act": 0.11, "wind_fcst": 17681.1, "wind_act": 14590.28, "net_load_fcst": 39136.5497, "net_load_act": null, "hsl_outage": 6722.0}, {"date": "2026-07-20", "he": 4, "load_fcst": 55398.0893, "load_act": null, "solar_fcst": 0.0, "solar_act": 0.11, "wind_fcst": 16500.1, "wind_act": 14116.15, "net_load_fcst": 38897.9893, "net_load_act": null, "hsl_outage": 6722.0}, {"date": "2026-07-20", "he": 5, "load_fcst": 54886.4499, "load_act": null, "solar_fcst": 0.0, "solar_act": 0.08, "wind_fcst": 15227.0, "wind_act": 13359.58, "net_load_fcst": 39659.4499, "net_load_act": null, "hsl_outage": 6722.0}, {"date": "2026-07-20", "he": 6, "load_fcst": 55344.81, "load_act": null, "solar_fcst": 0.0, "solar_act": 0.08, "wind_fcst": 13847.1, "wind_act": 13166.4, "net_load_fcst": 41497.71, "net_load_act": null, "hsl_outage": 6722.0}, {"date": "2026-07-20", "he": 7, "load_fcst": 56195.6397, "load_act": null, "solar_fcst": 134.4, "solar_act": 78.94, "wind_fcst": 12469.6, "wind_act": 12622.18, "net_load_fcst": 43591.6397, "net_load_act": null, "hsl_outage": 6922.0}, {"date": "2026-07-20", "he": 8, "load_fcst": 57170.7305, "load_act": null, "solar_fcst": 5601.5, "solar_act": null, "wind_fcst": 11544.7, "wind_act": null, "net_load_fcst": 40024.53049999999, "net_load_act": null, "hsl_outage": 6856.0}, {"date": "2026-07-20", "he": 9, "load_fcst": 60600.0201, "load_act": null, "solar_fcst": 19480.3, "solar_act": null, "wind_fcst": 11057.5, "wind_act": null, "net_load_fcst": 30062.220100000006, "net_load_act": null, "hsl_outage": 6986.0}, {"date": "2026-07-20", "he": 10, "load_fcst": 64951.1396, "load_act": null, "solar_fcst": 27730.7, "solar_act": null, "wind_fcst": 10549.7, "wind_act": null, "net_load_fcst": 26670.739599999997, "net_load_act": null, "hsl_outage": 6933.0}, {"date": "2026-07-20", "he": 11, "load_fcst": 70035.7611, "load_act": null, "solar_fcst": 31057.1, "solar_act": null, "wind_fcst": 10048.9, "wind_act": null, "net_load_fcst": 28929.761100000003, "net_load_act": null, "hsl_outage": 6933.0}, {"date": "2026-07-20", "he": 12, "load_fcst": 74669.6301, "load_act": null, "solar_fcst": 32837.6, "solar_act": null, "wind_fcst": 9533.9, "wind_act": null, "net_load_fcst": 32298.130099999995, "net_load_act": null, "hsl_outage": 6743.0}, {"date": "2026-07-20", "he": 13, "load_fcst": 79000.1409, "load_act": null, "solar_fcst": 33388.6, "solar_act": null, "wind_fcst": 9017.1, "wind_act": null, "net_load_fcst": 36594.4409, "net_load_act": null, "hsl_outage": 6890.0}, {"date": "2026-07-20", "he": 14, "load_fcst": 82617.2686, "load_act": null, "solar_fcst": 33483.1, "solar_act": null, "wind_fcst": 9708.5, "wind_act": null, "net_load_fcst": 39425.6686, "net_load_act": null, "hsl_outage": 6880.0}, {"date": "2026-07-20", "he": 15, "load_fcst": 84770.2891, "load_act": null, "solar_fcst": 33383.4, "solar_act": null, "wind_fcst": 10805.3, "wind_act": null, "net_load_fcst": 40581.5891, "net_load_act": null, "hsl_outage": 6835.0}, {"date": "2026-07-20", "he": 16, "load_fcst": 85903.9509, "load_act": null, "solar_fcst": 32833.7, "solar_act": null, "wind_fcst": 11901.5, "wind_act": null, "net_load_fcst": 41168.7509, "net_load_act": null, "hsl_outage": 6635.0}, {"date": "2026-07-20", "he": 17, "load_fcst": 86357.6405, "load_act": null, "solar_fcst": 32393.7, "solar_act": null, "wind_fcst": 12944.7, "wind_act": null, "net_load_fcst": 41019.2405, "net_load_act": null, "hsl_outage": 6635.0}, {"date": "2026-07-20", "he": 18, "load_fcst": 86682.7892, "load_act": null, "solar_fcst": 30763.2, "solar_act": null, "wind_fcst": 13914.0, "wind_act": null, "net_load_fcst": 42005.5892, "net_load_act": null, "hsl_outage": 6459.0}, {"date": "2026-07-20", "he": 19, "load_fcst": 85996.719, "load_act": null, "solar_fcst": 25434.1, "solar_act": null, "wind_fcst": 15536.7, "wind_act": null, "net_load_fcst": 45025.918999999994, "net_load_act": null, "hsl_outage": 6355.0}, {"date": "2026-07-20", "he": 20, "load_fcst": 83751.6093, "load_act": null, "solar_fcst": 11827.5, "solar_act": null, "wind_fcst": 17164.1, "wind_act": null, "net_load_fcst": 54760.0093, "net_load_act": null, "hsl_outage": 6205.0}, {"date": "2026-07-20", "he": 21, "load_fcst": 80258.9006, "load_act": null, "solar_fcst": 1049.8, "solar_act": null, "wind_fcst": 17761.8, "wind_act": null, "net_load_fcst": 61447.30059999999, "net_load_act": null, "hsl_outage": 6177.0}, {"date": "2026-07-20", "he": 22, "load_fcst": 77385.8499, "load_act": null, "solar_fcst": 0.0, "solar_act": null, "wind_fcst": 18360.2, "wind_act": null, "net_load_fcst": 59025.649900000004, "net_load_act": null, "hsl_outage": 6177.0}, {"date": "2026-07-20", "he": 23, "load_fcst": 73159.0611, "load_act": null, "solar_fcst": 0.0, "solar_act": null, "wind_fcst": 18816.5, "wind_act": null, "net_load_fcst": 54342.561100000006, "net_load_act": null, "hsl_outage": 6337.0}, {"date": "2026-07-20", "he": 24, "load_fcst": 68653.0801, "load_act": null, "solar_fcst": 0.0, "solar_act": null, "wind_fcst": 19102.6, "wind_act": null, "net_load_fcst": 49550.48010000001, "net_load_act": null, "hsl_outage": 6058.0}, {"date": "2026-07-21", "he": 1, "load_fcst": 64490.1504, "load_act": null, "solar_fcst": 0.0, "solar_act": null, "wind_fcst": 19386.5, "wind_act": null, "net_load_fcst": 45103.6504, "net_load_act": null, "hsl_outage": 6058.0}, {"date": "2026-07-21", "he": 2, "load_fcst": 61033.5095, "load_act": null, "solar_fcst": 0.0, "solar_act": null, "wind_fcst": 19225.0, "wind_act": null, "net_load_fcst": 41808.5095, "net_load_act": null, "hsl_outage": 6058.0}, {"date": "2026-07-21", "he": 3, "load_fcst": 58444.3602, "load_act": null, "solar_fcst": 0.0, "solar_act": null, "wind_fcst": 16958.9, "wind_act": null, "net_load_fcst": 41485.4602, "net_load_act": null, "hsl_outage": 6058.0}, {"date": "2026-07-21", "he": 4, "load_fcst": 56677.2308, "load_act": null, "solar_fcst": 0.0, "solar_act": null, "wind_fcst": 15763.1, "wind_act": null, "net_load_fcst": 40914.1308, "net_load_act": null, "hsl_outage": 6058.0}, {"date": "2026-07-21", "he": 5, "load_fcst": 55941.6103, "load_act": null, "solar_fcst": 0.0, "solar_act": null, "wind_fcst": 14555.5, "wind_act": null, "net_load_fcst": 41386.1103, "net_load_act": null, "hsl_outage": 6058.0}, {"date": "2026-07-21", "he": 6, "load_fcst": 56337.5997, "load_act": null, "solar_fcst": 0.0, "solar_act": null, "wind_fcst": 13335.6, "wind_act": null, "net_load_fcst": 43001.9997, "net_load_act": null, "hsl_outage": 6068.0}, {"date": "2026-07-21", "he": 7, "load_fcst": 57082.8992, "load_act": null, "solar_fcst": 119.8, "solar_act": null, "wind_fcst": 11281.1, "wind_act": null, "net_load_fcst": 45681.9992, "net_load_act": null, "hsl_outage": 6068.0}, {"date": "2026-07-21", "he": 8, "load_fcst": 57745.93, "load_act": null, "solar_fcst": 5144.1, "solar_act": null, "wind_fcst": 10411.9, "wind_act": null, "net_load_fcst": 42189.93, "net_load_act": null, "hsl_outage": 5908.0}, {"date": "2026-07-21", "he": 9, "load_fcst": 60831.19, "load_act": null, "solar_fcst": 18123.8, "solar_act": null, "wind_fcst": 10114.4, "wind_act": null, "net_load_fcst": 32592.989999999998, "net_load_act": null, "hsl_outage": 5918.0}, {"date": "2026-07-21", "he": 10, "load_fcst": 65336.68, "load_act": null, "solar_fcst": 25955.7, "solar_act": null, "wind_fcst": 9825.4, "wind_act": null, "net_load_fcst": 29555.579999999994, "net_load_act": null, "hsl_outage": 5918.0}, {"date": "2026-07-21", "he": 11, "load_fcst": 70597.5005, "load_act": null, "solar_fcst": 28768.2, "solar_act": null, "wind_fcst": 9615.3, "wind_act": null, "net_load_fcst": 32214.0005, "net_load_act": null, "hsl_outage": 5911.0}, {"date": "2026-07-21", "he": 12, "load_fcst": 75594.6983, "load_act": null, "solar_fcst": 30543.8, "solar_act": null, "wind_fcst": 9504.2, "wind_act": null, "net_load_fcst": 35546.698300000004, "net_load_act": null, "hsl_outage": 5491.0}, {"date": "2026-07-21", "he": 13, "load_fcst": 80340.1303, "load_act": null, "solar_fcst": 31300.3, "solar_act": null, "wind_fcst": 9397.5, "wind_act": null, "net_load_fcst": 39642.3303, "net_load_act": null, "hsl_outage": 5491.0}, {"date": "2026-07-21", "he": 14, "load_fcst": 84342.8801, "load_act": null, "solar_fcst": 31276.3, "solar_act": null, "wind_fcst": 8326.7, "wind_act": null, "net_load_fcst": 44739.880099999995, "net_load_act": null, "hsl_outage": 5481.0}, {"date": "2026-07-21", "he": 15, "load_fcst": 86457.1093, "load_act": null, "solar_fcst": 31067.8, "solar_act": null, "wind_fcst": 9303.7, "wind_act": null, "net_load_fcst": 46085.6093, "net_load_act": null, "hsl_outage": 5481.0}, {"date": "2026-07-21", "he": 16, "load_fcst": 87474.3504, "load_act": null, "solar_fcst": 30333.1, "solar_act": null, "wind_fcst": 10300.2, "wind_act": null, "net_load_fcst": 46841.05039999999, "net_load_act": null, "hsl_outage": 5481.0}, {"date": "2026-07-21", "he": 17, "load_fcst": 87896.5591, "load_act": null, "solar_fcst": 30039.6, "solar_act": null, "wind_fcst": 11265.1, "wind_act": null, "net_load_fcst": 46591.8591, "net_load_act": null, "hsl_outage": 5471.0}, {"date": "2026-07-21", "he": 18, "load_fcst": 88219.6695, "load_act": null, "solar_fcst": 28174.7, "solar_act": null, "wind_fcst": 12207.6, "wind_act": null, "net_load_fcst": 47837.36950000001, "net_load_act": null, "hsl_outage": 5471.0}, {"date": "2026-07-21", "he": 19, "load_fcst": 87655.2212, "load_act": null, "solar_fcst": 23037.8, "solar_act": null, "wind_fcst": 11832.5, "wind_act": null, "net_load_fcst": 52784.9212, "net_load_act": null, "hsl_outage": 5416.0}, {"date": "2026-07-21", "he": 20, "load_fcst": 85753.3696, "load_act": null, "solar_fcst": 10748.1, "solar_act": null, "wind_fcst": 12773.6, "wind_act": null, "net_load_fcst": 62231.6696, "net_load_act": null, "hsl_outage": 5416.0}, {"date": "2026-07-21", "he": 21, "load_fcst": 82415.929, "load_act": null, "solar_fcst": 968.2, "solar_act": null, "wind_fcst": 13391.4, "wind_act": null, "net_load_fcst": 68056.32900000001, "net_load_act": null, "hsl_outage": 5416.0}, {"date": "2026-07-21", "he": 22, "load_fcst": 79576.8098, "load_act": null, "solar_fcst": 0.0, "solar_act": null, "wind_fcst": 13998.9, "wind_act": null, "net_load_fcst": 65577.90980000001, "net_load_act": null, "hsl_outage": 5416.0}, {"date": "2026-07-21", "he": 23, "load_fcst": 75312.8506, "load_act": null, "solar_fcst": 0.0, "solar_act": null, "wind_fcst": 14340.6, "wind_act": null, "net_load_fcst": 60972.25060000001, "net_load_act": null, "hsl_outage": 5416.0}, {"date": "2026-07-21", "he": 24, "load_fcst": 70831.31, "load_act": null, "solar_fcst": 0.0, "solar_act": null, "wind_fcst": 14361.0, "wind_act": null, "net_load_fcst": 56470.31, "net_load_act": null, "hsl_outage": 4752.0}, {"date": "2026-07-22", "he": 1, "load_fcst": 66609.8289, "load_act": null, "solar_fcst": 0.0, "solar_act": null, "wind_fcst": 14384.6, "wind_act": null, "net_load_fcst": 52225.228899999995, "net_load_act": null, "hsl_outage": 4752.0}, {"date": "2026-07-22", "he": 2, "load_fcst": 63438.6691, "load_act": null, "solar_fcst": 0.0, "solar_act": null, "wind_fcst": 15670.4, "wind_act": null, "net_load_fcst": 47768.2691, "net_load_act": null, "hsl_outage": 4752.0}, {"date": "2026-07-22", "he": 3, "load_fcst": 61016.3705, "load_act": null, "solar_fcst": 0.0, "solar_act": null, "wind_fcst": 14362.4, "wind_act": null, "net_load_fcst": 46653.970499999996, "net_load_act": null, "hsl_outage": 4752.0}, {"date": "2026-07-22", "he": 4, "load_fcst": 59399.6898, "load_act": null, "solar_fcst": 0.0, "solar_act": null, "wind_fcst": 13060.1, "wind_act": null, "net_load_fcst": 46339.5898, "net_load_act": null, "hsl_outage": 5152.0}, {"date": "2026-07-22", "he": 5, "load_fcst": 58559.9206, "load_act": null, "solar_fcst": 0.0, "solar_act": null, "wind_fcst": 11759.5, "wind_act": null, "net_load_fcst": 46800.4206, "net_load_act": null, "hsl_outage": 5152.0}, {"date": "2026-07-22", "he": 6, "load_fcst": 58877.08, "load_act": null, "solar_fcst": 0.0, "solar_act": null, "wind_fcst": 10460.2, "wind_act": null, "net_load_fcst": 48416.880000000005, "net_load_act": null, "hsl_outage": 4752.0}, {"date": "2026-07-22", "he": 7, "load_fcst": 59541.129400000005, "load_act": null, "solar_fcst": 107.8, "solar_act": null, "wind_fcst": 10352.0, "wind_act": null, "net_load_fcst": 49081.3294, "net_load_act": null, "hsl_outage": 4752.0}, {"date": "2026-07-22", "he": 8, "load_fcst": 60502.7515, "load_act": null, "solar_fcst": 5122.6, "solar_act": null, "wind_fcst": 9663.6, "wind_act": null, "net_load_fcst": 45716.5515, "net_load_act": null, "hsl_outage": 4752.0}, {"date": "2026-07-22", "he": 9, "load_fcst": 63630.7304, "load_act": null, "solar_fcst": 18598.6, "solar_act": null, "wind_fcst": 8996.6, "wind_act": null, "net_load_fcst": 36035.5304, "net_load_act": null, "hsl_outage": 4752.0}, {"date": "2026-07-22", "he": 10, "load_fcst": 68293.4982, "load_act": null, "solar_fcst": 26814.7, "solar_act": null, "wind_fcst": 8329.9, "wind_act": null, "net_load_fcst": 33148.8982, "net_load_act": null, "hsl_outage": 4762.0}, {"date": "2026-07-22", "he": 11, "load_fcst": 73663.5715, "load_act": null, "solar_fcst": 30475.5, "solar_act": null, "wind_fcst": 7648.1, "wind_act": null, "net_load_fcst": 35539.97150000001, "net_load_act": null, "hsl_outage": 4472.0}, {"date": "2026-07-22", "he": 12, "load_fcst": 78732.1114, "load_act": null, "solar_fcst": 32332.0, "solar_act": null, "wind_fcst": 6947.9, "wind_act": null, "net_load_fcst": 39452.21139999999, "net_load_act": null, "hsl_outage": 4472.0}, {"date": "2026-07-22", "he": 13, "load_fcst": 82493.5211, "load_act": null, "solar_fcst": 33117.7, "solar_act": null, "wind_fcst": 7038.7, "wind_act": null, "net_load_fcst": 42337.121100000004, "net_load_act": null, "hsl_outage": 4462.0}, {"date": "2026-07-22", "he": 14, "load_fcst": 85537.4894, "load_act": null, "solar_fcst": 33549.1, "solar_act": null, "wind_fcst": 7221.9, "wind_act": null, "net_load_fcst": 44766.489400000006, "net_load_act": null, "hsl_outage": 4462.0}, {"date": "2026-07-22", "he": 15, "load_fcst": 87218.1616, "load_act": null, "solar_fcst": 33506.6, "solar_act": null, "wind_fcst": 8435.7, "wind_act": null, "net_load_fcst": 45275.861600000004, "net_load_act": null, "hsl_outage": 4462.0}, {"date": "2026-07-22", "he": 16, "load_fcst": 88248.8805, "load_act": null, "solar_fcst": 33043.2, "solar_act": null, "wind_fcst": 9850.1, "wind_act": null, "net_load_fcst": 45355.580500000004, "net_load_act": null, "hsl_outage": 4462.0}, {"date": "2026-07-22", "he": 17, "load_fcst": 88790.10979999999, "load_act": null, "solar_fcst": 33224.6, "solar_act": null, "wind_fcst": 11344.4, "wind_act": null, "net_load_fcst": 44221.10979999999, "net_load_act": null, "hsl_outage": 4462.0}, {"date": "2026-07-22", "he": 18, "load_fcst": 88961.74919999999, "load_act": null, "solar_fcst": 31885.8, "solar_act": null, "wind_fcst": 12941.3, "wind_act": null, "net_load_fcst": 44134.649199999985, "net_load_act": null, "hsl_outage": 4452.0}, {"date": "2026-07-22", "he": 19, "load_fcst": 88055.38070000001, "load_act": null, "solar_fcst": 26570.3, "solar_act": null, "wind_fcst": 13709.0, "wind_act": null, "net_load_fcst": 47776.080700000006, "net_load_act": null, "hsl_outage": 4449.0}, {"date": "2026-07-22", "he": 20, "load_fcst": 86126.1911, "load_act": null, "solar_fcst": 12274.1, "solar_act": null, "wind_fcst": 15069.0, "wind_act": null, "net_load_fcst": 58783.09109999999, "net_load_act": null, "hsl_outage": 4419.0}, {"date": "2026-07-22", "he": 21, "load_fcst": 83914.469, "load_act": null, "solar_fcst": 1071.9, "solar_act": null, "wind_fcst": 16309.7, "wind_act": null, "net_load_fcst": 66532.869, "net_load_act": null, "hsl_outage": 4419.0}, {"date": "2026-07-22", "he": 22, "load_fcst": 81936.2608, "load_act": null, "solar_fcst": 0.0, "solar_act": null, "wind_fcst": 17516.1, "wind_act": null, "net_load_fcst": 64420.160800000005, "net_load_act": null, "hsl_outage": 4374.0}, {"date": "2026-07-22", "he": 23, "load_fcst": 77509.2993, "load_act": null, "solar_fcst": 0.0, "solar_act": null, "wind_fcst": 18440.0, "wind_act": null, "net_load_fcst": 59069.2993, "net_load_act": null, "hsl_outage": 4374.0}, {"date": "2026-07-22", "he": 24, "load_fcst": 72670.3101, "load_act": null, "solar_fcst": 0.0, "solar_act": null, "wind_fcst": 19007.0, "wind_act": null, "net_load_fcst": 53663.3101, "net_load_act": null, "hsl_outage": 4317.0}, {"date": "2026-07-23", "he": 1, "load_fcst": 67461.1795, "load_act": null, "solar_fcst": 0.0, "solar_act": null, "wind_fcst": 19064.5, "wind_act": null, "net_load_fcst": 48396.6795, "net_load_act": null, "hsl_outage": 4317.0}, {"date": "2026-07-23", "he": 2, "load_fcst": 63949.3594, "load_act": null, "solar_fcst": 0.0, "solar_act": null, "wind_fcst": 18934.8, "wind_act": null, "net_load_fcst": 45014.5594, "net_load_act": null, "hsl_outage": 4317.0}, {"date": "2026-07-23", "he": 3, "load_fcst": 61259.4201, "load_act": null, "solar_fcst": 0.0, "solar_act": null, "wind_fcst": 17534.1, "wind_act": null, "net_load_fcst": 43725.320100000004, "net_load_act": null, "hsl_outage": 4317.0}, {"date": "2026-07-23", "he": 4, "load_fcst": 59488.3408, "load_act": null, "solar_fcst": 0.0, "solar_act": null, "wind_fcst": 16452.5, "wind_act": null, "net_load_fcst": 43035.8408, "net_load_act": null, "hsl_outage": 4317.0}, {"date": "2026-07-23", "he": 5, "load_fcst": 58684.859599999996, "load_act": null, "solar_fcst": 0.0, "solar_act": null, "wind_fcst": 15270.6, "wind_act": null, "net_load_fcst": 43414.2596, "net_load_act": null, "hsl_outage": 4317.0}, {"date": "2026-07-23", "he": 6, "load_fcst": 59220.1501, "load_act": null, "solar_fcst": 0.0, "solar_act": null, "wind_fcst": 13969.2, "wind_act": null, "net_load_fcst": 45250.9501, "net_load_act": null, "hsl_outage": 4317.0}, {"date": "2026-07-23", "he": 7, "load_fcst": 59669.0216, "load_act": null, "solar_fcst": 109.5, "solar_act": null, "wind_fcst": 11819.6, "wind_act": null, "net_load_fcst": 47739.9216, "net_load_act": null, "hsl_outage": 4317.0}, {"date": "2026-07-23", "he": 8, "load_fcst": 60352.5396, "load_act": null, "solar_fcst": 5500.4, "solar_act": null, "wind_fcst": 10341.0, "wind_act": null, "net_load_fcst": 44511.139599999995, "net_load_act": null, "hsl_outage": 4317.0}, {"date": "2026-07-23", "he": 9, "load_fcst": 63387.7688, "load_act": null, "solar_fcst": 20101.7, "solar_act": null, "wind_fcst": 9088.7, "wind_act": null, "net_load_fcst": 34197.3688, "net_load_act": null, "hsl_outage": 4317.0}, {"date": "2026-07-23", "he": 10, "load_fcst": 67803.92020000001, "load_act": null, "solar_fcst": 28744.0, "solar_act": null, "wind_fcst": 7838.4, "wind_act": null, "net_load_fcst": 31221.520200000006, "net_load_act": null, "hsl_outage": 4327.0}, {"date": "2026-07-23", "he": 11, "load_fcst": 72666.2194, "load_act": null, "solar_fcst": 31689.5, "solar_act": null, "wind_fcst": 6733.5, "wind_act": null, "net_load_fcst": 34243.2194, "net_load_act": null, "hsl_outage": 4327.0}, {"date": "2026-07-23", "he": 12, "load_fcst": 77141.6515, "load_act": null, "solar_fcst": 33092.9, "solar_act": null, "wind_fcst": 5809.0, "wind_act": null, "net_load_fcst": 38239.751500000006, "net_load_act": null, "hsl_outage": 4327.0}, {"date": "2026-07-23", "he": 13, "load_fcst": 81036.6787, "load_act": null, "solar_fcst": 33573.1, "solar_act": null, "wind_fcst": 4884.0, "wind_act": null, "net_load_fcst": 42579.578700000005, "net_load_act": null, "hsl_outage": 4317.0}, {"date": "2026-07-23", "he": 14, "load_fcst": 84324.7895, "load_act": null, "solar_fcst": 34038.8, "solar_act": null, "wind_fcst": 4409.4, "wind_act": null, "net_load_fcst": 45876.589499999995, "net_load_act": null, "hsl_outage": 4317.0}, {"date": "2026-07-23", "he": 15, "load_fcst": 85888.3198, "load_act": null, "solar_fcst": 33853.6, "solar_act": null, "wind_fcst": 5753.1, "wind_act": null, "net_load_fcst": 46281.6198, "net_load_act": null, "hsl_outage": 4317.0}, {"date": "2026-07-23", "he": 16, "load_fcst": 86536.9302, "load_act": null, "solar_fcst": 33468.3, "solar_act": null, "wind_fcst": 7095.9, "wind_act": null, "net_load_fcst": 45972.7302, "net_load_act": null, "hsl_outage": 4317.0}, {"date": "2026-07-23", "he": 17, "load_fcst": 86678.6718, "load_act": null, "solar_fcst": 33808.2, "solar_act": null, "wind_fcst": 8560.1, "wind_act": null, "net_load_fcst": 44310.3718, "net_load_act": null, "hsl_outage": 4317.0}, {"date": "2026-07-23", "he": 18, "load_fcst": 86686.5292, "load_act": null, "solar_fcst": 32433.2, "solar_act": null, "wind_fcst": 10171.2, "wind_act": null, "net_load_fcst": 44082.12920000001, "net_load_act": null, "hsl_outage": 4317.0}, {"date": "2026-07-23", "he": 19, "load_fcst": 86184.721, "load_act": null, "solar_fcst": 26868.8, "solar_act": null, "wind_fcst": 11874.9, "wind_act": null, "net_load_fcst": 47441.021, "net_load_act": null, "hsl_outage": 4317.0}, {"date": "2026-07-23", "he": 20, "load_fcst": 84538.8499, "load_act": null, "solar_fcst": 11953.8, "solar_act": null, "wind_fcst": 13620.0, "wind_act": null, "net_load_fcst": 58965.0499, "net_load_act": null, "hsl_outage": 4317.0}, {"date": "2026-07-23", "he": 21, "load_fcst": 81662.8887, "load_act": null, "solar_fcst": 985.3, "solar_act": null, "wind_fcst": 15115.0, "wind_act": null, "net_load_fcst": 65562.5887, "net_load_act": null, "hsl_outage": 4317.0}, {"date": "2026-07-23", "he": 22, "load_fcst": 79281.9998, "load_act": null, "solar_fcst": 0.0, "solar_act": null, "wind_fcst": 16556.9, "wind_act": null, "net_load_fcst": 62725.0998, "net_load_act": null, "hsl_outage": 4317.0}, {"date": "2026-07-23", "he": 23, "load_fcst": 75448.1597, "load_act": null, "solar_fcst": 0.0, "solar_act": null, "wind_fcst": 17745.2, "wind_act": null, "net_load_fcst": 57702.95970000001, "net_load_act": null, "hsl_outage": 4317.0}, {"date": "2026-07-23", "he": 24, "load_fcst": 71195.6884, "load_act": null, "solar_fcst": 0.0, "solar_act": null, "wind_fcst": 18623.8, "wind_act": null, "net_load_fcst": 52571.888399999996, "net_load_act": null, "hsl_outage": 4317.0}, {"date": "2026-07-24", "he": 1, "load_fcst": 67242.4794, "load_act": null, "solar_fcst": 0.0, "solar_act": null, "wind_fcst": 19540.9, "wind_act": null, "net_load_fcst": 47701.579399999995, "net_load_act": null, "hsl_outage": 4317.0}, {"date": "2026-07-24", "he": 2, "load_fcst": 63854.829, "load_act": null, "solar_fcst": 0.0, "solar_act": null, "wind_fcst": 19798.0, "wind_act": null, "net_load_fcst": 44056.829, "net_load_act": null, "hsl_outage": 4317.0}, {"date": "2026-07-24", "he": 3, "load_fcst": 61233.4092, "load_act": null, "solar_fcst": 0.0, "solar_act": null, "wind_fcst": 18791.5, "wind_act": null, "net_load_fcst": 42441.9092, "net_load_act": null, "hsl_outage": 4317.0}, {"date": "2026-07-24", "he": 4, "load_fcst": 59481.7602, "load_act": null, "solar_fcst": 0.0, "solar_act": null, "wind_fcst": 17785.7, "wind_act": null, "net_load_fcst": 41696.06019999999, "net_load_act": null, "hsl_outage": 4317.0}, {"date": "2026-07-24", "he": 5, "load_fcst": 58702.6107, "load_act": null, "solar_fcst": 0.0, "solar_act": null, "wind_fcst": 16678.5, "wind_act": null, "net_load_fcst": 42024.1107, "net_load_act": null, "hsl_outage": 4317.0}, {"date": "2026-07-24", "he": 6, "load_fcst": 58891.4706, "load_act": null, "solar_fcst": 0.0, "solar_act": null, "wind_fcst": 15451.7, "wind_act": null, "net_load_fcst": 43439.7706, "net_load_act": null, "hsl_outage": 4317.0}, {"date": "2026-07-24", "he": 7, "load_fcst": 59315.3396, "load_act": null, "solar_fcst": 100.4, "solar_act": null, "wind_fcst": 14511.7, "wind_act": null, "net_load_fcst": 44703.2396, "net_load_act": null, "hsl_outage": 4317.0}, {"date": "2026-07-24", "he": 8, "load_fcst": 60158.2393, "load_act": null, "solar_fcst": 5267.7, "solar_act": null, "wind_fcst": 13245.5, "wind_act": null, "net_load_fcst": 41645.039300000004, "net_load_act": null, "hsl_outage": 4317.0}, {"date": "2026-07-24", "he": 9, "load_fcst": 63284.0902, "load_act": null, "solar_fcst": 19589.8, "solar_act": null, "wind_fcst": 11911.5, "wind_act": null, "net_load_fcst": 31782.790200000003, "net_load_act": null, "hsl_outage": 4317.0}, {"date": "2026-07-24", "he": 10, "load_fcst": 67738.9096, "load_act": null, "solar_fcst": 28405.6, "solar_act": null, "wind_fcst": 10577.1, "wind_act": null, "net_load_fcst": 28756.209600000002, "net_load_act": null, "hsl_outage": 4317.0}, {"date": "2026-07-24", "he": 11, "load_fcst": 72617.13, "load_act": null, "solar_fcst": 31293.0, "solar_act": null, "wind_fcst": 9237.8, "wind_act": null, "net_load_fcst": 32086.330000000005, "net_load_act": null, "hsl_outage": 4317.0}, {"date": "2026-07-24", "he": 12, "load_fcst": 77015.6982, "load_act": null, "solar_fcst": 32684.7, "solar_act": null, "wind_fcst": 7897.4, "wind_act": null, "net_load_fcst": 36433.5982, "net_load_act": null, "hsl_outage": 4317.0}, {"date": "2026-07-24", "he": 13, "load_fcst": 80948.4409, "load_act": null, "solar_fcst": 33373.7, "solar_act": null, "wind_fcst": 6553.9, "wind_act": null, "net_load_fcst": 41020.8409, "net_load_act": null, "hsl_outage": 4311.0}, {"date": "2026-07-24", "he": 14, "load_fcst": 84162.7397, "load_act": null, "solar_fcst": 33667.6, "solar_act": null, "wind_fcst": 8118.7, "wind_act": null, "net_load_fcst": 42376.43970000001, "net_load_act": null, "hsl_outage": 4311.0}, {"date": "2026-07-24", "he": 15, "load_fcst": 85428.9201, "load_act": null, "solar_fcst": 33537.5, "solar_act": null, "wind_fcst": 9607.8, "wind_act": null, "net_load_fcst": 42283.6201, "net_load_act": null, "hsl_outage": 4311.0}, {"date": "2026-07-24", "he": 16, "load_fcst": 85668.7912, "load_act": null, "solar_fcst": 32972.4, "solar_act": null, "wind_fcst": 11098.0, "wind_act": null, "net_load_fcst": 41598.391200000005, "net_load_act": null, "hsl_outage": 4311.0}, {"date": "2026-07-24", "he": 17, "load_fcst": 85564.7994, "load_act": null, "solar_fcst": 32838.3, "solar_act": null, "wind_fcst": 12823.3, "wind_act": null, "net_load_fcst": 39903.1994, "net_load_act": null, "hsl_outage": 4311.0}, {"date": "2026-07-24", "he": 18, "load_fcst": 85344.6211, "load_act": null, "solar_fcst": 31352.1, "solar_act": null, "wind_fcst": 14829.9, "wind_act": null, "net_load_fcst": 39162.621100000004, "net_load_act": null, "hsl_outage": 4311.0}, {"date": "2026-07-24", "he": 19, "load_fcst": 84680.3199, "load_act": null, "solar_fcst": 25935.5, "solar_act": null, "wind_fcst": 17188.8, "wind_act": null, "net_load_fcst": 41556.0199, "net_load_act": null, "hsl_outage": 4311.0}, {"date": "2026-07-24", "he": 20, "load_fcst": 82922.2503, "load_act": null, "solar_fcst": 11724.3, "solar_act": null, "wind_fcst": 19243.6, "wind_act": null, "net_load_fcst": 51954.3503, "net_load_act": null, "hsl_outage": 4311.0}, {"date": "2026-07-24", "he": 21, "load_fcst": 79974.6294, "load_act": null, "solar_fcst": 1002.8, "solar_act": null, "wind_fcst": 20252.1, "wind_act": null, "net_load_fcst": 58719.729400000004, "net_load_act": null, "hsl_outage": 4311.0}, {"date": "2026-07-24", "he": 22, "load_fcst": 77804.6209, "load_act": null, "solar_fcst": 0.0, "solar_act": null, "wind_fcst": 21259.5, "wind_act": null, "net_load_fcst": 56545.120899999994, "net_load_act": null, "hsl_outage": 4311.0}, {"date": "2026-07-24", "he": 23, "load_fcst": 74321.3797, "load_act": null, "solar_fcst": 0.0, "solar_act": null, "wind_fcst": 21931.4, "wind_act": null, "net_load_fcst": 52389.9797, "net_load_act": null, "hsl_outage": 4311.0}, {"date": "2026-07-24", "he": 24, "load_fcst": 70435.4492, "load_act": null, "solar_fcst": 0.0, "solar_act": null, "wind_fcst": 22146.7, "wind_act": null, "net_load_fcst": 48288.749200000006, "net_load_act": null, "hsl_outage": 3887.0}, {"date": "2026-07-25", "he": 1, "load_fcst": 66465.2802, "load_act": null, "solar_fcst": 0.0, "solar_act": null, "wind_fcst": 22441.8, "wind_act": null, "net_load_fcst": 44023.48019999999, "net_load_act": null, "hsl_outage": 3887.0}, {"date": "2026-07-25", "he": 2, "load_fcst": 63076.299, "load_act": null, "solar_fcst": 0.0, "solar_act": null, "wind_fcst": 22393.8, "wind_act": null, "net_load_fcst": 40682.498999999996, "net_load_act": null, "hsl_outage": 3887.0}, {"date": "2026-07-25", "he": 3, "load_fcst": 60266.9096, "load_act": null, "solar_fcst": 0.0, "solar_act": null, "wind_fcst": 21547.6, "wind_act": null, "net_load_fcst": 38719.3096, "net_load_act": null, "hsl_outage": 3887.0}, {"date": "2026-07-25", "he": 4, "load_fcst": 58331.2198, "load_act": null, "solar_fcst": 0.0, "solar_act": null, "wind_fcst": 20702.3, "wind_act": null, "net_load_fcst": 37628.9198, "net_load_act": null, "hsl_outage": 3887.0}, {"date": "2026-07-25", "he": 5, "load_fcst": 57057.6808, "load_act": null, "solar_fcst": 0.0, "solar_act": null, "wind_fcst": 19755.4, "wind_act": null, "net_load_fcst": 37302.2808, "net_load_act": null, "hsl_outage": 3887.0}, {"date": "2026-07-25", "he": 6, "load_fcst": 56285.6897, "load_act": null, "solar_fcst": 0.0, "solar_act": null, "wind_fcst": 18687.5, "wind_act": null, "net_load_fcst": 37598.1897, "net_load_act": null, "hsl_outage": 3887.0}, {"date": "2026-07-25", "he": 7, "load_fcst": 55653.9198, "load_act": null, "solar_fcst": 93.0, "solar_act": null, "wind_fcst": 17619.5, "wind_act": null, "net_load_fcst": 37941.4198, "net_load_act": null, "hsl_outage": 3887.0}, {"date": "2026-07-25", "he": 8, "load_fcst": 56246.1194, "load_act": null, "solar_fcst": 5093.1, "solar_act": null, "wind_fcst": 16032.9, "wind_act": null, "net_load_fcst": 35120.1194, "net_load_act": null, "hsl_outage": 3887.0}, {"date": "2026-07-25", "he": 9, "load_fcst": 59701.979400000004, "load_act": null, "solar_fcst": 19232.0, "solar_act": null, "wind_fcst": 15110.3, "wind_act": null, "net_load_fcst": 25359.679400000005, "net_load_act": null, "hsl_outage": 3887.0}, {"date": "2026-07-25", "he": 10, "load_fcst": 64480.6501, "load_act": null, "solar_fcst": 27789.8, "solar_act": null, "wind_fcst": 14191.7, "wind_act": null, "net_load_fcst": 22499.150099999995, "net_load_act": null, "hsl_outage": 3887.0}, {"date": "2026-07-25", "he": 11, "load_fcst": 69359.6594, "load_act": null, "solar_fcst": 30967.3, "solar_act": null, "wind_fcst": 13147.9, "wind_act": null, "net_load_fcst": 25244.4594, "net_load_act": null, "hsl_outage": 3887.0}, {"date": "2026-07-25", "he": 12, "load_fcst": 73895.461, "load_act": null, "solar_fcst": 32615.9, "solar_act": null, "wind_fcst": 11962.6, "wind_act": null, "net_load_fcst": 29316.960999999996, "net_load_act": null, "hsl_outage": 3887.0}, {"date": "2026-07-25", "he": 13, "load_fcst": 77936.8106, "load_act": null, "solar_fcst": 33137.6, "solar_act": null, "wind_fcst": 10784.2, "wind_act": null, "net_load_fcst": 34015.010599999994, "net_load_act": null, "hsl_outage": 3887.0}, {"date": "2026-07-25", "he": 14, "load_fcst": 81133.93920000001, "load_act": null, "solar_fcst": 33266.5, "solar_act": null, "wind_fcst": 9776.9, "wind_act": null, "net_load_fcst": 38090.53920000001, "net_load_act": null, "hsl_outage": 3887.0}, {"date": "2026-07-25", "he": 15, "load_fcst": 82910.1701, "load_act": null, "solar_fcst": 32962.8, "solar_act": null, "wind_fcst": 11038.8, "wind_act": null, "net_load_fcst": 38908.5701, "net_load_act": null, "hsl_outage": 3887.0}, {"date": "2026-07-25", "he": 16, "load_fcst": 83959.2815, "load_act": null, "solar_fcst": 32283.5, "solar_act": null, "wind_fcst": 12299.6, "wind_act": null, "net_load_fcst": 39376.1815, "net_load_act": null, "hsl_outage": 3887.0}, {"date": "2026-07-25", "he": 17, "load_fcst": 84291.2603, "load_act": null, "solar_fcst": 32499.0, "solar_act": null, "wind_fcst": 13677.8, "wind_act": null, "net_load_fcst": 38114.46029999999, "net_load_act": null, "hsl_outage": 3887.0}, {"date": "2026-07-25", "he": 18, "load_fcst": 84419.5289, "load_act": null, "solar_fcst": 30723.9, "solar_act": null, "wind_fcst": 15358.5, "wind_act": null, "net_load_fcst": 38337.1289, "net_load_act": null, "hsl_outage": 3887.0}, {"date": "2026-07-25", "he": 19, "load_fcst": 83860.5814, "load_act": null, "solar_fcst": 25065.6, "solar_act": null, "wind_fcst": 15022.6, "wind_act": null, "net_load_fcst": 43772.3814, "net_load_act": null, "hsl_outage": 3887.0}, {"date": "2026-07-25", "he": 20, "load_fcst": 82272.7205, "load_act": null, "solar_fcst": 11104.1, "solar_act": null, "wind_fcst": 16604.8, "wind_act": null, "net_load_fcst": 54563.82049999999, "net_load_act": null, "hsl_outage": 3887.0}, {"date": "2026-07-25", "he": 21, "load_fcst": 79408.9309, "load_act": null, "solar_fcst": 932.0, "solar_act": null, "wind_fcst": 18248.4, "wind_act": null, "net_load_fcst": 60228.530900000005, "net_load_act": null, "hsl_outage": 3887.0}, {"date": "2026-07-25", "he": 22, "load_fcst": 77376.6596, "load_act": null, "solar_fcst": 0.0, "solar_act": null, "wind_fcst": 19891.4, "wind_act": null, "net_load_fcst": 57485.2596, "net_load_act": null, "hsl_outage": 3887.0}, {"date": "2026-07-25", "he": 23, "load_fcst": 73867.0895, "load_act": null, "solar_fcst": 0.0, "solar_act": null, "wind_fcst": 21187.0, "wind_act": null, "net_load_fcst": 52680.0895, "net_load_act": null, "hsl_outage": 3887.0}, {"date": "2026-07-25", "he": 24, "load_fcst": 70039.3705, "load_act": null, "solar_fcst": 0.0, "solar_act": null, "wind_fcst": 22037.3, "wind_act": null, "net_load_fcst": 48002.0705, "net_load_act": null, "hsl_outage": 3887.0}, {"date": "2026-07-26", "he": 1, "load_fcst": 65929.7188, "load_act": null, "solar_fcst": 0.0, "solar_act": null, "wind_fcst": 23086.2, "wind_act": null, "net_load_fcst": 42843.518800000005, "net_load_act": null, "hsl_outage": 3887.0}, {"date": "2026-07-26", "he": 2, "load_fcst": 63081.8409, "load_act": null, "solar_fcst": 0.0, "solar_act": null, "wind_fcst": 22322.8, "wind_act": null, "net_load_fcst": 40759.04090000001, "net_load_act": null, "hsl_outage": 3887.0}, {"date": "2026-07-26", "he": 3, "load_fcst": 60771.8788, "load_act": null, "solar_fcst": 0.0, "solar_act": null, "wind_fcst": 21584.4, "wind_act": null, "net_load_fcst": 39187.4788, "net_load_act": null, "hsl_outage": 3887.0}, {"date": "2026-07-26", "he": 4, "load_fcst": 59019.3896, "load_act": null, "solar_fcst": 0.0, "solar_act": null, "wind_fcst": 20838.6, "wind_act": null, "net_load_fcst": 38180.789600000004, "net_load_act": null, "hsl_outage": 3887.0}, {"date": "2026-07-26", "he": 5, "load_fcst": 57842.7197, "load_act": null, "solar_fcst": 0.0, "solar_act": null, "wind_fcst": 20012.5, "wind_act": null, "net_load_fcst": 37830.2197, "net_load_act": null, "hsl_outage": 3887.0}, {"date": "2026-07-26", "he": 6, "load_fcst": 57098.4699, "load_act": null, "solar_fcst": 0.0, "solar_act": null, "wind_fcst": 19098.4, "wind_act": null, "net_load_fcst": 38000.069899999995, "net_load_act": null, "hsl_outage": 3887.0}, {"date": "2026-07-26", "he": 7, "load_fcst": 56294.02, "load_act": null, "solar_fcst": 74.6, "solar_act": null, "wind_fcst": 18183.2, "wind_act": null, "net_load_fcst": 38036.22, "net_load_act": null, "hsl_outage": 3887.0}, {"date": "2026-07-26", "he": 8, "load_fcst": 56560.989799999996, "load_act": null, "solar_fcst": 4405.5, "solar_act": null, "wind_fcst": 14911.1, "wind_act": null, "net_load_fcst": 37244.3898, "net_load_act": null, "hsl_outage": 3887.0}, {"date": "2026-07-26", "he": 9, "load_fcst": 59367.0305, "load_act": null, "solar_fcst": 16939.9, "solar_act": null, "wind_fcst": 13942.3, "wind_act": null, "net_load_fcst": 28484.8305, "net_load_act": null, "hsl_outage": 3887.0}, {"date": "2026-07-26", "he": 10, "load_fcst": 63755.9098, "load_act": null, "solar_fcst": 25117.0, "solar_act": null, "wind_fcst": 12974.5, "wind_act": null, "net_load_fcst": 25664.4098, "net_load_act": null, "hsl_outage": 3887.0}, {"date": "2026-07-26", "he": 11, "load_fcst": 68339.23939999999, "load_act": null, "solar_fcst": 28456.4, "solar_act": null, "wind_fcst": 11993.7, "wind_act": null, "net_load_fcst": 27889.13939999999, "net_load_act": null, "hsl_outage": 3887.0}, {"date": "2026-07-26", "he": 12, "load_fcst": 73661.0304, "load_act": null, "solar_fcst": 30238.0, "solar_act": null, "wind_fcst": 10999.8, "wind_act": null, "net_load_fcst": 32423.230400000004, "net_load_act": null, "hsl_outage": 3887.0}, {"date": "2026-07-26", "he": 13, "load_fcst": 77430.4414, "load_act": null, "solar_fcst": 31293.2, "solar_act": null, "wind_fcst": 10006.6, "wind_act": null, "net_load_fcst": 36130.6414, "net_load_act": null, "hsl_outage": 3887.0}, {"date": "2026-07-26", "he": 14, "load_fcst": 80491.8498, "load_act": null, "solar_fcst": 32726.9, "solar_act": null, "wind_fcst": 9954.0, "wind_act": null, "net_load_fcst": 37810.949799999995, "net_load_act": null, "hsl_outage": 3887.0}, {"date": "2026-07-26", "he": 15, "load_fcst": 82325.1695, "load_act": null, "solar_fcst": 32427.3, "solar_act": null, "wind_fcst": 10815.3, "wind_act": null, "net_load_fcst": 39082.5695, "net_load_act": null, "hsl_outage": 3887.0}, {"date": "2026-07-26", "he": 16, "load_fcst": 83468.7595, "load_act": null, "solar_fcst": 31753.6, "solar_act": null, "wind_fcst": 11677.7, "wind_act": null, "net_load_fcst": 40037.4595, "net_load_act": null, "hsl_outage": 3887.0}, {"date": "2026-07-26", "he": 17, "load_fcst": 83922.811, "load_act": null, "solar_fcst": 31637.1, "solar_act": null, "wind_fcst": 12656.8, "wind_act": null, "net_load_fcst": 39628.91100000001, "net_load_act": null, "hsl_outage": 3887.0}, {"date": "2026-07-26", "he": 18, "load_fcst": 84214.3996, "load_act": null, "solar_fcst": 29697.7, "solar_act": null, "wind_fcst": 13809.0, "wind_act": null, "net_load_fcst": 40707.69960000001, "net_load_act": null, "hsl_outage": 3887.0}, {"date": "2026-07-26", "he": 19, "load_fcst": 83690.9202, "load_act": null, "solar_fcst": 24014.4, "solar_act": null, "wind_fcst": 16351.1, "wind_act": null, "net_load_fcst": 43325.42019999999, "net_load_act": null, "hsl_outage": 3887.0}, {"date": "2026-07-26", "he": 20, "load_fcst": 81928.32, "load_act": null, "solar_fcst": 10423.3, "solar_act": null, "wind_fcst": 17648.2, "wind_act": null, "net_load_fcst": 53856.82000000001, "net_load_act": null, "hsl_outage": 3887.0}, {"date": "2026-07-26", "he": 21, "load_fcst": 79155.5111, "load_act": null, "solar_fcst": 814.1, "solar_act": null, "wind_fcst": 19070.9, "wind_act": null, "net_load_fcst": 59270.511099999996, "net_load_act": null, "hsl_outage": 3887.0}, {"date": "2026-07-26", "he": 22, "load_fcst": 77016.3498, "load_act": null, "solar_fcst": 0.0, "solar_act": null, "wind_fcst": 20486.0, "wind_act": null, "net_load_fcst": 56530.349799999996, "net_load_act": null, "hsl_outage": 3887.0}, {"date": "2026-07-26", "he": 23, "load_fcst": 73561.0289, "load_act": null, "solar_fcst": 0.0, "solar_act": null, "wind_fcst": 21588.8, "wind_act": null, "net_load_fcst": 51972.2289, "net_load_act": null, "hsl_outage": 3887.0}, {"date": "2026-07-26", "he": 24, "load_fcst": 69776.9509, "load_act": null, "solar_fcst": 0.0, "solar_act": null, "wind_fcst": 22346.9, "wind_act": null, "net_load_fcst": 47430.050899999995, "net_load_act": null, "hsl_outage": 3887.0}, {"date": "2026-07-27", "he": 1, "load_fcst": 65066.6897, "load_act": null, "solar_fcst": 0.0, "solar_act": null, "wind_fcst": 23131.3, "wind_act": null, "net_load_fcst": 41935.3897, "net_load_act": null, "hsl_outage": 3887.0}, {"date": "2026-07-27", "he": 2, "load_fcst": 62158.3885, "load_act": null, "solar_fcst": 0.0, "solar_act": null, "wind_fcst": 23429.1, "wind_act": null, "net_load_fcst": 38729.2885, "net_load_act": null, "hsl_outage": 3887.0}, {"date": "2026-07-27", "he": 3, "load_fcst": 59982.2305, "load_act": null, "solar_fcst": 0.0, "solar_act": null, "wind_fcst": 22398.4, "wind_act": null, "net_load_fcst": 37583.8305, "net_load_act": null, "hsl_outage": 3887.0}, {"date": "2026-07-27", "he": 4, "load_fcst": 58469.5001, "load_act": null, "solar_fcst": 0.0, "solar_act": null, "wind_fcst": 21365.8, "wind_act": null, "net_load_fcst": 37103.7001, "net_load_act": null, "hsl_outage": 3887.0}, {"date": "2026-07-27", "he": 5, "load_fcst": 57863.37, "load_act": null, "solar_fcst": 0.0, "solar_act": null, "wind_fcst": 20241.6, "wind_act": null, "net_load_fcst": 37621.770000000004, "net_load_act": null, "hsl_outage": 3887.0}, {"date": "2026-07-27", "he": 6, "load_fcst": 58377.9307, "load_act": null, "solar_fcst": 0.0, "solar_act": null, "wind_fcst": 19008.3, "wind_act": null, "net_load_fcst": 39369.630699999994, "net_load_act": null, "hsl_outage": 3887.0}, {"date": "2026-07-27", "he": 7, "load_fcst": 58997.7506, "load_act": null, "solar_fcst": 79.7, "solar_act": null, "wind_fcst": 17524.4, "wind_act": null, "net_load_fcst": 41393.6506, "net_load_act": null, "hsl_outage": 3887.0}, {"date": "2026-07-27", "he": 8, "load_fcst": 59911.56, "load_act": null, "solar_fcst": null, "solar_act": null, "wind_fcst": null, "wind_act": null, "net_load_fcst": null, "net_load_act": null, "hsl_outage": 3887.0}, {"date": "2026-07-27", "he": 9, "load_fcst": 63049.7895, "load_act": null, "solar_fcst": null, "solar_act": null, "wind_fcst": null, "wind_act": null, "net_load_fcst": null, "net_load_act": null, "hsl_outage": 3887.0}, {"date": "2026-07-27", "he": 10, "load_fcst": 67453.0992, "load_act": null, "solar_fcst": null, "solar_act": null, "wind_fcst": null, "wind_act": null, "net_load_fcst": null, "net_load_act": null, "hsl_outage": 3887.0}, {"date": "2026-07-27", "he": 11, "load_fcst": 72259.6087, "load_act": null, "solar_fcst": null, "solar_act": null, "wind_fcst": null, "wind_act": null, "net_load_fcst": null, "net_load_act": null, "hsl_outage": 3887.0}, {"date": "2026-07-27", "he": 12, "load_fcst": 76650.161, "load_act": null, "solar_fcst": null, "solar_act": null, "wind_fcst": null, "wind_act": null, "net_load_fcst": null, "net_load_act": null, "hsl_outage": 3887.0}, {"date": "2026-07-27", "he": 13, "load_fcst": 80534.4402, "load_act": null, "solar_fcst": null, "solar_act": null, "wind_fcst": null, "wind_act": null, "net_load_fcst": null, "net_load_act": null, "hsl_outage": 3887.0}, {"date": "2026-07-27", "he": 14, "load_fcst": 83695.76, "load_act": null, "solar_fcst": null, "solar_act": null, "wind_fcst": null, "wind_act": null, "net_load_fcst": null, "net_load_act": null, "hsl_outage": 3887.0}, {"date": "2026-07-27", "he": 15, "load_fcst": 85227.9504, "load_act": null, "solar_fcst": null, "solar_act": null, "wind_fcst": null, "wind_act": null, "net_load_fcst": null, "net_load_act": null, "hsl_outage": 3887.0}, {"date": "2026-07-27", "he": 16, "load_fcst": 85845.2597, "load_act": null, "solar_fcst": null, "solar_act": null, "wind_fcst": null, "wind_act": null, "net_load_fcst": null, "net_load_act": null, "hsl_outage": 3887.0}, {"date": "2026-07-27", "he": 17, "load_fcst": 86100.0891, "load_act": null, "solar_fcst": null, "solar_act": null, "wind_fcst": null, "wind_act": null, "net_load_fcst": null, "net_load_act": null, "hsl_outage": 3887.0}, {"date": "2026-07-27", "he": 18, "load_fcst": 86233.8193, "load_act": null, "solar_fcst": null, "solar_act": null, "wind_fcst": null, "wind_act": null, "net_load_fcst": null, "net_load_act": null, "hsl_outage": 3887.0}, {"date": "2026-07-27", "he": 19, "load_fcst": 85745.9795, "load_act": null, "solar_fcst": null, "solar_act": null, "wind_fcst": null, "wind_act": null, "net_load_fcst": null, "net_load_act": null, "hsl_outage": 3887.0}, {"date": "2026-07-27", "he": 20, "load_fcst": 84074.17, "load_act": null, "solar_fcst": null, "solar_act": null, "wind_fcst": null, "wind_act": null, "net_load_fcst": null, "net_load_act": null, "hsl_outage": 3887.0}, {"date": "2026-07-27", "he": 21, "load_fcst": 81066.8582, "load_act": null, "solar_fcst": null, "solar_act": null, "wind_fcst": null, "wind_act": null, "net_load_fcst": null, "net_load_act": null, "hsl_outage": 3887.0}, {"date": "2026-07-27", "he": 22, "load_fcst": 78464.8594, "load_act": null, "solar_fcst": null, "solar_act": null, "wind_fcst": null, "wind_act": null, "net_load_fcst": null, "net_load_act": null, "hsl_outage": 3887.0}, {"date": "2026-07-27", "he": 23, "load_fcst": 74583.8507, "load_act": null, "solar_fcst": null, "solar_act": null, "wind_fcst": null, "wind_act": null, "net_load_fcst": null, "net_load_act": null, "hsl_outage": 3887.0}, {"date": "2026-07-27", "he": 24, "load_fcst": 70435.8593, "load_act": null, "solar_fcst": null, "solar_act": null, "wind_fcst": null, "wind_act": null, "net_load_fcst": null, "net_load_act": null, "hsl_outage": null}]}